Workbook

Sheet Costos
A1: COSTOS Y PRECIOS
A2: Completá solo las celdas amarillas. El resto se calcula solo.
A4: 1. PACKAGING
A5: Componente | B5: Precio del pack | C5: Unidades | D5: Costo por pieza | E5: Descripción del pedido | F5: Notas
A6: Sticker isotipo | B6: 18000 | C6: 330 | D6: =IFERROR(B6/C6,0) -> 54.545455 | E6: Ideas Argentinas. Redondo 3,5 cm, fondo chocolate con la O manteca, papel adhesivo, troquelado incluido. 1 plancha de 29x40 cm = $1.600 + IVA. Producción normal 48/72 hs. Falta que confirmen cuántos entran por plancha (estimado 70, con 3 mm entre siluetas). | F6: fijarme el color para pagarle a roxana e imprimir
A7: Etiqueta interior | B7: 3450 | C7: 60 | D7: =IFERROR(B7/C7,0) -> 57.5 | E7: Ideas Argentinas. Tarjeta 8x5 cm horizontal, ilustración 300 gr, frente y dorso. Frente con logo, dorso manteca liso. Entran 30 por hoja A3+ (31x46 cm). 2 impresiones = $2.300 + IVA = 60 tarjetas. Mitad plata 925, mitad acero blanco. | F7: tengo que ir a retirar a larralde
A8: Papel seda | B8: 1600 | C8: 10 | D8: =IFERROR(B8/C8,0) -> 160 | F8: fijarme si sirven las tarjetas interiores
A9: Caja Kraft | B9: 18718 | C9: 30 | D9: =IFERROR(B9/C9,0) -> 623.93333 | F9: compre en smartpackaging, me queda retirarlo x ramallo
A10: Sticker cerrar bolsa | B10: 18000 | C10: 130 | D10: =IFERROR(B10/C10,0) -> 138.46154 | F10: mande a studioimage falta q contesten
A11: Bolsa autoadhesiva | B11: 3220 | C11: 100 | D11: =IFERROR(B11/C11,0) -> 32.2 | E11: Bolsa autoadhesiva 6x11 | F11: compre por ML tengo que retirarlo
A12: Bolsa con manija | B12: 25000 | C12: 100 | D12: =IFERROR(B12/C12,0) -> 250 | E12: Bolsa de papel con manija para entregas en mano. Sin cotizar todavía.
A13: TOTAL PACKAGING POR PIEZA | D13: =SUM(D6:D12) -> 1316.6403
A17: 2. MIS REGLAS
A18: Multiplico el costo por | B18: 2 | C18: El precio sugerido es el doble del costo total (joya + packaging).
A19: Comisión de la venta | B19: 0 | C19: Poné 0% si cobrás por transferencia.
A21: 3. PRODUCTOS
A22: Producto | B22: Material | C22: Categoría | D22: Proveedor | E22: Link de la publicación | F22: Costo de compra | G22: Descuento | H22: Packaging | I22: Costo total | J22: Precio sugerido | K22: Precio de venta | L22: Ganancia por unidad | M22: Margen
A23: Argollitas Classic N°1 | B23: Plata 925 | C23: Aros | D23: Docha | E23: Cubano N°0 | F23: 2845 | G23: 0.1 | H23: =IF($A23="","",$D$13) -> 1316.6403 | I23: =IF($A23="","",N(F23)*(1-N(G23))+N(H23)) -> 3877.1403 | J23: =IF($A23="","",CEILING(I23*$B$18,500)) -> 8000 | K23: 7000 | L23: =IF(OR($A23="",N(K23)=0),"",K23-K23*$B$19-N(I23)) -> 3122.8597 | M23: =IF(OR($A23="",N(K23)=0),"",N(L23)/K23) -> 0.44612281 | N23: ← ejemplos, pisalos con tus productos
A24: Argollitas Classic N°2 | B24: Plata 925 | C24: Aros | D24: Docha | E24: Cubano N°1 | F24: 3405 | G24: 0.1 | H24: =IF($A24="","",$D$13) -> 1316.6403 | I24: =IF($A24="","",N(F24)*(1-N(G24))+N(H24)) -> 4381.1403 | J24: =IF($A24="","",CEILING(I24*$B$18,500)) -> 9000 | K24: 7500 | L24: =IF(OR($A24="",N(K24)=0),"",K24-K24*$B$19-N(I24)) -> 3118.8597 | M24: =IF(OR($A24="",N(K24)=0),"",N(L24)/K24) -> 0.41584796
A25: Argollitas Classic N°3 | B25: Plata 925 | C25: Aros | D25: Docha | E25: Cubano N°2 | F25: 3965 | G25: 0.1 | H25: =IF($A25="","",$D$13) -> 1316.6403 | I25: =IF($A25="","",N(F25)*(1-N(G25))+N(H25)) -> 4885.1403 | J25: =IF($A25="","",CEILING(I25*$B$18,500)) -> 10000 | K25: 8000 | L25: =IF(OR($A25="",N(K25)=0),"",K25-K25*$B$19-N(I25)) -> 3114.8597 | M25: =IF(OR($A25="",N(K25)=0),"",N(L25)/K25) -> 0.38935746
A26: Argollitas Classic N°4 | B26: Plata 925 | C26: Aros | D26: Docha | E26: Cubano N°3 | F26: 4525 | G26: 0.1 | H26: =IF($A26="","",$D$13) -> 1316.6403 | I26: =IF($A26="","",N(F26)*(1-N(G26))+N(H26)) -> 5389.1403 | J26: =IF($A26="","",CEILING(I26*$B$18,500)) -> 11000 | K26: 8500 | L26: =IF(OR($A26="",N(K26)=0),"",K26-K26*$B$19-N(I26)) -> 3110.8597 | M26: =IF(OR($A26="",N(K26)=0),"",N(L26)/K26) -> 0.36598349
A27: Argollitas Classic N°5 | B27: Plata 925 | C27: Aros | D27: Docha | E27: Cubano N°4 | F27: 4805 | G27: 0.1 | H27: =IF($A27="","",$D$13) -> 1316.6403 | I27: =IF($A27="","",N(F27)*(1-N(G27))+N(H27)) -> 5641.1403 | J27: =IF($A27="","",CEILING(I27*$B$18,500)) -> 11500 | K27: 9000 | L27: =IF(OR($A27="",N(K27)=0),"",K27-K27*$B$19-N(I27)) -> 3358.8597 | M27: =IF(OR($A27="",N(K27)=0),"",N(L27)/K27) -> 0.37320663
A28: Cubic Mini Circulo | B28: Plata 925 | C28: Aros | D28: Docha | E28: Mini susanita 2mm | F28: 6400 | G28: 0.1 | H28: =IF($A28="","",$D$13) -> 1316.6403 | I28: =IF($A28="","",N(F28)*(1-N(G28))+N(H28)) -> 7076.6403 | J28: =IF($A28="","",CEILING(I28*$B$18,500)) -> 14500 | K28: 12000 | L28: =IF(OR($A28="",N(K28)=0),"",K28-K28*$B$19-N(I28)) -> 4923.3597 | M28: =IF(OR($A28="",N(K28)=0),"",N(L28)/K28) -> 0.41027997
A29: Cubic Circulo Docha | B29: Plata 925 | C29: Aros | D29: Docha | E29: Mini susanita 3mm | F29: 6800 | G29: 0.1 | H29: =IF($A29="","",$D$13) -> 1316.6403 | I29: =IF($A29="","",N(F29)*(1-N(G29))+N(H29)) -> 7436.6403 | J29: =IF($A29="","",CEILING(I29*$B$18,500)) -> 15000 | K29: 12500 | L29: =IF(OR($A29="",N(K29)=0),"",K29-K29*$B$19-N(I29)) -> 5063.3597 | M29: =IF(OR($A29="",N(K29)=0),"",N(L29)/K29) -> 0.40506877
A30: Cubic Cuadrado | B30: Plata 925 | C30: Aros | D30: Docha | E30: Cuadrado cubic 4mm | F30: 6270 | G30: 0.1 | H30: =IF($A30="","",$D$13) -> 1316.6403 | I30: =IF($A30="","",N(F30)*(1-N(G30))+N(H30)) -> 6959.6403 | J30: =IF($A30="","",CEILING(I30*$B$18,500)) -> 14000 | K30: 12500 | L30: =IF(OR($A30="",N(K30)=0),"",K30-K30*$B$19-N(I30)) -> 5540.3597 | M30: =IF(OR($A30="",N(K30)=0),"",N(L30)/K30) -> 0.44322877
A31: Argollitas Marco Docha | B31: Plata 925 | C31: Aros | D31: Docha | E31: - | F31: 18645 | G31: 0.1 | H31: =IF($A31="","",$D$13) -> 1316.6403 | I31: =IF($A31="","",N(F31)*(1-N(G31))+N(H31)) -> 18097.14 | J31: =IF($A31="","",CEILING(I31*$B$18,500)) -> 36500 | K31: 25000 | L31: =IF(OR($A31="",N(K31)=0),"",K31-K31*$B$19-N(I31)) -> 6902.8597 | M31: =IF(OR($A31="",N(K31)=0),"",N(L31)/K31) -> 0.27611439
A32: Anillo Circulo | B32: Plata 925 | C32: Anillo | D32: Docha | E32: Anillo circulo | F32: 8250 | G32: 0.1 | H32: =IF($A32="","",$D$13) -> 1316.6403 | I32: =IF($A32="","",N(F32)*(1-N(G32))+N(H32)) -> 8741.6403 | J32: =IF($A32="","",CEILING(I32*$B$18,500)) -> 17500 | K32: 16000 | L32: =IF(OR($A32="",N(K32)=0),"",K32-K32*$B$19-N(I32)) -> 7258.3597 | M32: =IF(OR($A32="",N(K32)=0),"",N(L32)/K32) -> 0.45364748
A33: Anillo Gota | B33: Plata 925 | C33: Anillo | D33: Docha | E33: - | F33: 14148 | G33: 0.1 | H33: =IF($A33="","",$D$13) -> 1316.6403 | I33: =IF($A33="","",N(F33)*(1-N(G33))+N(H33)) -> 14049.84 | J33: =IF($A33="","",CEILING(I33*$B$18,500)) -> 28500 | K33: 23000 | L33: =IF(OR($A33="",N(K33)=0),"",K33-K33*$B$19-N(I33)) -> 8950.1597 | M33: =IF(OR($A33="",N(K33)=0),"",N(L33)/K33) -> 0.38913738
A34: Anillo Vera Docha | B34: Plata 925 | C34: Anillo | D34: Docha | E34: Anillo V | F34: 6500 | G34: 0.1 | H34: =IF($A34="","",$D$13) -> 1316.6403 | I34: =IF($A34="","",N(F34)*(1-N(G34))+N(H34)) -> 7166.6403 | J34: =IF($A34="","",CEILING(I34*$B$18,500)) -> 14500 | K34: 13000 | L34: =IF(OR($A34="",N(K34)=0),"",K34-K34*$B$19-N(I34)) -> 5833.3597 | M34: =IF(OR($A34="",N(K34)=0),"",N(L34)/K34) -> 0.44871997
A35: Anillo Calado | B35: Plata 925 | C35: Anillo | D35: Docha | E35: Anillo calado | F35: 10890 | G35: 0.1 | H35: =IF($A35="","",$D$13) -> 1316.6403 | I35: =IF($A35="","",N(F35)*(1-N(G35))+N(H35)) -> 11117.64 | J35: =IF($A35="","",CEILING(I35*$B$18,500)) -> 22500 | K35: 19000 | L35: =IF(OR($A35="",N(K35)=0),"",K35-K35*$B$19-N(I35)) -> 7882.3597 | M35: =IF(OR($A35="",N(K35)=0),"",N(L35)/K35) -> 0.41486104
A36: Cadena eslabon | B36: Acero blanco | C36: Collar | D36: Docha | E36: https://dochajoyaspormayor.com.ar/tienda/john-caladito/ | F36: 3900 | G36: 0.1 | H36: =IF($A36="","",$D$13) -> 1316.6403 | I36: =IF($A36="","",N(F36)*(1-N(G36))+N(H36)) -> 4826.6403 | J36: =IF($A36="","",CEILING(I36*$B$18,500)) -> 10000 | K36: 8500 | L36: =IF(OR($A36="",N(K36)=0),"",K36-K36*$B$19-N(I36)) -> 3673.3597 | M36: =IF(OR($A36="",N(K36)=0),"",N(L36)/K36) -> 0.43215996
A37: Cadena lisa | B37: Acero blanco | C37: Collar | D37: Docha | F37: 2700 | G37: 0.1 | H37: =IF($A37="","",$D$13) -> 1316.6403 | I37: =IF($A37="","",N(F37)*(1-N(G37))+N(H37)) -> 3746.6403 | J37: =IF($A37="","",CEILING(I37*$B$18,500)) -> 7500 | K37: 7000 | L37: =IF(OR($A37="",N(K37)=0),"",K37-K37*$B$19-N(I37)) -> 3253.3597 | M37: =IF(OR($A37="",N(K37)=0),"",N(L37)/K37) -> 0.46476567
A38: Argollitas gota | B38: Acero blanco | C38: Aros | D38: Docha | F38: 3100 | G38: 0.1 | H38: =IF($A38="","",$D$13) -> 1316.6403 | I38: =IF($A38="","",N(F38)*(1-N(G38))+N(H38)) -> 4106.6403 | J38: =IF($A38="","",CEILING(I38*$B$18,500)) -> 8500 | K38: 7500 | L38: =IF(OR($A38="",N(K38)=0),"",K38-K38*$B$19-N(I38)) -> 3393.3597 | M38: =IF(OR($A38="",N(K38)=0),"",N(L38)/K38) -> 0.45244796
A39: Argollitas Caviar circulo | B39: Acero blanco | C39: Aros | D39: Docha | E39: https://dochajoyaspormayor.com.ar/tienda/click-bolitas/ | F39: 2300 | G39: 0.1 | H39: =IF($A39="","",$D$13) -> 1316.6403 | I39: =IF($A39="","",N(F39)*(1-N(G39))+N(H39)) -> 3386.6403 | J39: =IF($A39="","",CEILING(I39*$B$18,500)) -> 7000 | K39: 6500 | L39: =IF(OR($A39="",N(K39)=0),"",K39-K39*$B$19-N(I39)) -> 3113.3597 | M39: =IF(OR($A39="",N(K39)=0),"",N(L39)/K39) -> 0.47897841
A40: Argollitas Caviar triangulo | B40: Acero blanco | C40: Aros | D40: Docha | E40: https://dochajoyaspormayor.com.ar/tienda/bolitas-en-v/ | F40: 2300 | G40: 0.1 | H40: =IF($A40="","",$D$13) -> 1316.6403 | I40: =IF($A40="","",N(F40)*(1-N(G40))+N(H40)) -> 3386.6403 | J40: =IF($A40="","",CEILING(I40*$B$18,500)) -> 7000 | K40: 6500 | L40: =IF(OR($A40="",N(K40)=0),"",K40-K40*$B$19-N(I40)) -> 3113.3597 | M40: =IF(OR($A40="",N(K40)=0),"",N(L40)/K40) -> 0.47897841
A41: Argollitas Ocampo | B41: Acero blanco | C41: Aros | D41: Docha | E41: https://dochajoyaspormayor.com.ar/tienda/bolitas-en-v/ | F41: 3900 | G41: 0.1 | H41: =IF($A41="","",$D$13) -> 1316.6403 | I41: =IF($A41="","",N(F41)*(1-N(G41))+N(H41)) -> 4826.6403 | J41: =IF($A41="","",CEILING(I41*$B$18,500)) -> 10000 | K41: 7000 | L41: =IF(OR($A41="",N(K41)=0),"",K41-K41*$B$19-N(I41)) -> 2173.3597 | M41: =IF(OR($A41="",N(K41)=0),"",N(L41)/K41) -> 0.31047995
A42: Argollitas Bubble | B42: Acero blanco | C42: Aros | D42: Docha | F42: 3100 | G42: 0.1 | H42: =IF($A42="","",$D$13) -> 1316.6403 | I42: =IF($A42="","",N(F42)*(1-N(G42))+N(H42)) -> 4106.6403 | J42: =IF($A42="","",CEILING(I42*$B$18,500)) -> 8500 | K42: 6500 | L42: =IF(OR($A42="",N(K42)=0),"",K42-K42*$B$19-N(I42)) -> 2393.3597 | M42: =IF(OR($A42="",N(K42)=0),"",N(L42)/K42) -> 0.36820918
A43: Argollitas Bombe | B43: Acero blanco | C43: Aros | D43: Docha | E43: https://dochajoyaspormayor.com.ar/tienda/en-v-bombe/ | F43: 2600 | G43: 0.1 | H43: =IF($A43="","",$D$13) -> 1316.6403 | I43: =IF($A43="","",N(F43)*(1-N(G43))+N(H43)) -> 3656.6403 | J43: =IF($A43="","",CEILING(I43*$B$18,500)) -> 7500 | K43: 6500 | L43: =IF(OR($A43="",N(K43)=0),"",K43-K43*$B$19-N(I43)) -> 2843.3597 | M43: =IF(OR($A43="",N(K43)=0),"",N(L43)/K43) -> 0.43743995
A44: Argollita Duna N°0 | B44: Acero blanco | C44: Aros | D44: Docha | E44: https://dochajoyaspormayor.com.ar/tienda/carterita-snail/ | F44: 2200 | G44: 0.1 | H44: =IF($A44="","",$D$13) -> 1316.6403 | I44: =IF($A44="","",N(F44)*(1-N(G44))+N(H44)) -> 3296.6403 | J44: =IF($A44="","",CEILING(I44*$B$18,500)) -> 7000 | K44: 6500 | L44: =IF(OR($A44="",N(K44)=0),"",K44-K44*$B$19-N(I44)) -> 3203.3597 | M44: =IF(OR($A44="",N(K44)=0),"",N(L44)/K44) -> 0.49282457
A45: Argollita Duna N°1 | B45: Acero blanco | C45: Aros | D45: Docha | E45: https://dochajoyaspormayor.com.ar/tienda/carteritas-torce/ | F45: 2200 | G45: 0.1 | H45: =IF($A45="","",$D$13) -> 1316.6403 | I45: =IF($A45="","",N(F45)*(1-N(G45))+N(H45)) -> 3296.6403 | J45: =IF($A45="","",CEILING(I45*$B$18,500)) -> 7000 | K45: 6500 | L45: =IF(OR($A45="",N(K45)=0),"",K45-K45*$B$19-N(I45)) -> 3203.3597 | M45: =IF(OR($A45="",N(K45)=0),"",N(L45)/K45) -> 0.49282457
E46: https://dochajoyaspormayor.com.ar/tienda/carteritas-torce/ | H46: =IF($A46="","",$D$13) | I46: =IF($A46="","",N(F46)*(1-N(G46))+N(H46)) | J46: =IF($A46="","",CEILING(I46*$B$18,500)) | L46: =IF(OR($A46="",N(K46)=0),"",K46-K46*$B$19-N(I46)) | M46: =IF(OR($A46="",N(K46)=0),"",N(L46)/K46)
A47: Anillo Corazón I | B47: Acero inoxidable | C47: Anillo | D47: Blert | E47: gordo | F47: 6500 | H47: =IF($A47="","",$D$13) -> 1316.6403 | I47: =IF($A47="","",N(F47)*(1-N(G47))+N(H47)) -> 7816.6403 | J47: =IF($A47="","",CEILING(I47*$B$18,500)) -> 16000 | K47: 13000 | L47: =IF(OR($A47="",N(K47)=0),"",K47-K47*$B$19-N(I47)) -> 5183.3597 | M47: =IF(OR($A47="",N(K47)=0),"",N(L47)/K47) -> 0.39871997
A48: Anillo Ovalo | B48: Acero inoxidable | C48: Anillo | D48: Blert | F48: 4500 | H48: =IF($A48="","",$D$13) -> 1316.6403 | I48: =IF($A48="","",N(F48)*(1-N(G48))+N(H48)) -> 5816.6403 | J48: =IF($A48="","",CEILING(I48*$B$18,500)) -> 12000 | K48: 11500 | L48: =IF(OR($A48="",N(K48)=0),"",K48-K48*$B$19-N(I48)) -> 5683.3597 | M48: =IF(OR($A48="",N(K48)=0),"",N(L48)/K48) -> 0.49420519
A49: Anillo Star | B49: Acero inoxidable | C49: Anillo | D49: Blert | F49: 4500 | H49: =IF($A49="","",$D$13) -> 1316.6403 | I49: =IF($A49="","",N(F49)*(1-N(G49))+N(H49)) -> 5816.6403 | J49: =IF($A49="","",CEILING(I49*$B$18,500)) -> 12000 | K49: 11500 | L49: =IF(OR($A49="",N(K49)=0),"",K49-K49*$B$19-N(I49)) -> 5683.3597 | M49: =IF(OR($A49="",N(K49)=0),"",N(L49)/K49) -> 0.49420519
A50: Anillo Nodo | B50: Acero inoxidable | C50: Anillo | D50: Blert | E50: grandote con agujeros | F50: 6500 | H50: =IF($A50="","",$D$13) -> 1316.6403 | I50: =IF($A50="","",N(F50)*(1-N(G50))+N(H50)) -> 7816.6403 | J50: =IF($A50="","",CEILING(I50*$B$18,500)) -> 16000 | K50: 13000 | L50: =IF(OR($A50="",N(K50)=0),"",K50-K50*$B$19-N(I50)) -> 5183.3597 | M50: =IF(OR($A50="",N(K50)=0),"",N(L50)/K50) -> 0.39871997
A51: Anillo Corazón II Plateado | B51: Acero inoxidable | C51: Anillo | D51: Blert | E51: finito | F51: 5500 | H51: =IF($A51="","",$D$13) -> 1316.6403 | I51: =IF($A51="","",N(F51)*(1-N(G51))+N(H51)) -> 6816.6403 | J51: =IF($A51="","",CEILING(I51*$B$18,500)) -> 14000 | K51: 12000 | L51: =IF(OR($A51="",N(K51)=0),"",K51-K51*$B$19-N(I51)) -> 5183.3597 | M51: =IF(OR($A51="",N(K51)=0),"",N(L51)/K51) -> 0.43194664
A52: Anillo Irregular | B52: Acero inoxidable | C52: Anillo | D52: Blert | F52: 4500 | H52: =IF($A52="","",$D$13) -> 1316.6403 | I52: =IF($A52="","",N(F52)*(1-N(G52))+N(H52)) -> 5816.6403 | J52: =IF($A52="","",CEILING(I52*$B$18,500)) -> 12000 | K52: 11500 | L52: =IF(OR($A52="",N(K52)=0),"",K52-K52*$B$19-N(I52)) -> 5683.3597 | M52: =IF(OR($A52="",N(K52)=0),"",N(L52)/K52) -> 0.49420519
A53: Anillo Zafira | B53: Acero inoxidable | C53: Anillo | D53: Blert | E53: nodo pero chico | F53: 6500 | H53: =IF($A53="","",$D$13) -> 1316.6403 | I53: =IF($A53="","",N(F53)*(1-N(G53))+N(H53)) -> 7816.6403 | J53: =IF($A53="","",CEILING(I53*$B$18,500)) -> 16000 | K53: 13000 | L53: =IF(OR($A53="",N(K53)=0),"",K53-K53*$B$19-N(I53)) -> 5183.3597 | M53: =IF(OR($A53="",N(K53)=0),"",N(L53)/K53) -> 0.39871997
A54: Anillo Norix | B54: Acero inoxidable | C54: Anillo | D54: Blert | E54: agujeros cruzados valen | F54: 4500 | H54: =IF($A54="","",$D$13) -> 1316.6403 | I54: =IF($A54="","",N(F54)*(1-N(G54))+N(H54)) -> 5816.6403 | J54: =IF($A54="","",CEILING(I54*$B$18,500)) -> 12000 | K54: 11500 | L54: =IF(OR($A54="",N(K54)=0),"",K54-K54*$B$19-N(I54)) -> 5683.3597 | M54: =IF(OR($A54="",N(K54)=0),"",N(L54)/K54) -> 0.49420519
A55: Anillo Vanton | B55: Acero inoxidable | C55: Anillo | D55: Blert | E55: uno para arriba, otro para abajo | F55: 4500 | H55: =IF($A55="","",$D$13) -> 1316.6403 | I55: =IF($A55="","",N(F55)*(1-N(G55))+N(H55)) -> 5816.6403 | J55: =IF($A55="","",CEILING(I55*$B$18,500)) -> 12000 | K55: 11500 | L55: =IF(OR($A55="",N(K55)=0),"",K55-K55*$B$19-N(I55)) -> 5683.3597 | M55: =IF(OR($A55="",N(K55)=0),"",N(L55)/K55) -> 0.49420519
A56: Anillo Azmira | B56: Acero inoxidable | C56: Anillo | D56: Blert | E56: lineas cruzado | F56: 4500 | H56: =IF($A56="","",$D$13) -> 1316.6403 | I56: =IF($A56="","",N(F56)*(1-N(G56))+N(H56)) -> 5816.6403 | J56: =IF($A56="","",CEILING(I56*$B$18,500)) -> 12000 | K56: 11500 | L56: =IF(OR($A56="",N(K56)=0),"",K56-K56*$B$19-N(I56)) -> 5683.3597 | M56: =IF(OR($A56="",N(K56)=0),"",N(L56)/K56) -> 0.49420519
A57: Anillo Mina | B57: Acero inoxidable | C57: Anillo | D57: Blert | E57: cruzado ancho chapa | F57: 6500 | H57: =IF($A57="","",$D$13) -> 1316.6403 | I57: =IF($A57="","",N(F57)*(1-N(G57))+N(H57)) -> 7816.6403 | J57: =IF($A57="","",CEILING(I57*$B$18,500)) -> 16000 | K57: 13000 | L57: =IF(OR($A57="",N(K57)=0),"",K57-K57*$B$19-N(I57)) -> 5183.3597 | M57: =IF(OR($A57="",N(K57)=0),"",N(L57)/K57) -> 0.39871997
A58: Anillo Virel | B58: Acero inoxidable | C58: Anillo | D58: Blert | E58: termina con punta | F58: 5500 | H58: =IF($A58="","",$D$13) -> 1316.6403 | I58: =IF($A58="","",N(F58)*(1-N(G58))+N(H58)) -> 6816.6403 | J58: =IF($A58="","",CEILING(I58*$B$18,500)) -> 14000 | K58: 12000 | L58: =IF(OR($A58="",N(K58)=0),"",K58-K58*$B$19-N(I58)) -> 5183.3597 | M58: =IF(OR($A58="",N(K58)=0),"",N(L58)/K58) -> 0.43194664
H59: =IF($A59="","",$D$13) | I59: =IF($A59="","",N(F59)*(1-N(G59))+N(H59)) | J59: =IF($A59="","",CEILING(I59*$B$18,500)) | L59: =IF(OR($A59="",N(K59)=0),"",K59-K59*$B$19-N(I59)) | M59: =IF(OR($A59="",N(K59)=0),"",N(L59)/K59)
A60: Cubic Mini cuadrado | B60: Plata 925 | C60: Aros | D60: 925 ARG | E60: 3mm mide | F60: 3550 | H60: =IF($A60="","",$D$13) -> 1316.6403 | I60: =IF($A60="","",N(F60)*(1-N(G60))+N(H60)) -> 4866.6403 | J60: =IF($A60="","",CEILING(I60*$B$18,500)) -> 10000 | K60: 12000 | L60: =IF(OR($A60="",N(K60)=0),"",K60-K60*$B$19-N(I60)) -> 7133.3597 | M60: =IF(OR($A60="",N(K60)=0),"",N(L60)/K60) -> 0.59444664
A61: Aros Halo N°2 (14 mm) | B61: Plata 925 | C61: Aros | D61: 925 ARG | E61: https://925arg.com/product.php?id=18369&iddet=34487 | F61: 13500 | H61: =IF($A61="","",$D$13) -> 1316.6403 | I61: =IF($A61="","",N(F61)*(1-N(G61))+N(H61)) -> 14816.64 | J61: =IF($A61="","",CEILING(I61*$B$18,500)) -> 30000 | K61: 25000 | L61: =IF(OR($A61="",N(K61)=0),"",K61-K61*$B$19-N(I61)) -> 10183.36 | M61: =IF(OR($A61="",N(K61)=0),"",N(L61)/K61) -> 0.40733439
A62: Aros Gala (12 mm) | B62: Plata 925 | C62: Aros | D62: 925 ARG | E62: https://925arg.com/product.php?id=46433&iddet=76647 | F62: 15550 | H62: =IF($A62="","",$D$13) -> 1316.6403 | I62: =IF($A62="","",N(F62)*(1-N(G62))+N(H62)) -> 16866.64 | J62: =IF($A62="","",CEILING(I62*$B$18,500)) -> 34000 | K62: 27000 | L62: =IF(OR($A62="",N(K62)=0),"",K62-K62*$B$19-N(I62)) -> 10133.36 | M62: =IF(OR($A62="",N(K62)=0),"",N(L62)/K62) -> 0.37530962
A63: Argollitas 10mm | B63: Plata 925 | C63: Aros | D63: 925 ARG | E63: https://925arg.com/product.php?id=46433&iddet=76647 | F63: 1950 | H63: =IF($A63="","",$D$13) -> 1316.6403 | I63: =IF($A63="","",N(F63)*(1-N(G63))+N(H63)) -> 3266.6403 | J63: =IF($A63="","",CEILING(I63*$B$18,500)) -> 7000 | K63: 7000 | L63: =IF(OR($A63="",N(K63)=0),"",K63-K63*$B$19-N(I63)) -> 3733.3597 | M63: =IF(OR($A63="",N(K63)=0),"",N(L63)/K63) -> 0.5333371
A64: Anillos Corazones III | B64: Plata 925 | C64: Anillo | D64: 925 ARG | E64: https://925arg.com/product.php?id=52954&iddet=86020 | F64: 13750 | H64: =IF($A64="","",$D$13) -> 1316.6403 | I64: =IF($A64="","",N(F64)*(1-N(G64))+N(H64)) -> 15066.64 | J64: =IF($A64="","",CEILING(I64*$B$18,500)) -> 30500 | K64: 23500 | L64: =IF(OR($A64="",N(K64)=0),"",K64-K64*$B$19-N(I64)) -> 8433.3597 | M64: =IF(OR($A64="",N(K64)=0),"",N(L64)/K64) -> 0.35886637
A65: Anillo Vena | B65: Plata 925 | C65: Anillo | D65: 925 ARG | E65: https://925arg.com/product.php?id=43711&iddet=72660 | F65: 15400 | H65: =IF($A65="","",$D$13) -> 1316.6403 | I65: =IF($A65="","",N(F65)*(1-N(G65))+N(H65)) -> 16716.64 | J65: =IF($A65="","",CEILING(I65*$B$18,500)) -> 33500 | K65: 25000 | L65: =IF(OR($A65="",N(K65)=0),"",K65-K65*$B$19-N(I65)) -> 8283.3597 | M65: =IF(OR($A65="",N(K65)=0),"",N(L65)/K65) -> 0.33133439
A66: Anillo Deriva | B66: Plata 925 | C66: Anillo | D66: 925 ARG | E66: https://925arg.com/product.php?id=50175&iddet=81976 | F66: 16950 | H66: =IF($A66="","",$D$13) -> 1316.6403 | I66: =IF($A66="","",N(F66)*(1-N(G66))+N(H66)) -> 18266.64 | J66: =IF($A66="","",CEILING(I66*$B$18,500)) -> 37000 | K66: 25500 | L66: =IF(OR($A66="",N(K66)=0),"",K66-K66*$B$19-N(I66)) -> 7233.3597 | M66: =IF(OR($A66="",N(K66)=0),"",N(L66)/K66) -> 0.28366116
A67: Anillo Sin Fin | B67: Plata 925 | C67: Anillo | D67: 925 ARG | E67: https://925arg.com/product.php?id=21231&iddet=34524 | F67: 11600 | H67: =IF($A67="","",$D$13) -> 1316.6403 | I67: =IF($A67="","",N(F67)*(1-N(G67))+N(H67)) -> 12916.64 | J67: =IF($A67="","",CEILING(I67*$B$18,500)) -> 26000 | K67: 20000 | L67: =IF(OR($A67="",N(K67)=0),"",K67-K67*$B$19-N(I67)) -> 7083.3597 | M67: =IF(OR($A67="",N(K67)=0),"",N(L67)/K67) -> 0.35416798
A68: Collar Muna Circulo | B68: Plata 925 | C68: Collar | D68: 925 ARG | E68: https://925arg.com/product.php?id=1476&iddet=1827 | F68: 17250 | H68: =IF($A68="","",$D$13) -> 1316.6403 | I68: =IF($A68="","",N(F68)*(1-N(G68))+N(H68)) -> 18566.64 | J68: =IF($A68="","",CEILING(I68*$B$18,500)) -> 37500 | K68: 30000 | L68: =IF(OR($A68="",N(K68)=0),"",K68-K68*$B$19-N(I68)) -> 11433.36 | M68: =IF(OR($A68="",N(K68)=0),"",N(L68)/K68) -> 0.38111199
A69: Collar Muna Corazón | B69: Plata 925 | C69: Collar | D69: 925 ARG | E69: https://925arg.com/product.php?id=46642&iddet=76952 | F69: 18150 | H69: =IF($A69="","",$D$13) -> 1316.6403 | I69: =IF($A69="","",N(F69)*(1-N(G69))+N(H69)) -> 19466.64 | J69: =IF($A69="","",CEILING(I69*$B$18,500)) -> 39000 | K69: 31000 | L69: =IF(OR($A69="",N(K69)=0),"",K69-K69*$B$19-N(I69)) -> 11533.36 | M69: =IF(OR($A69="",N(K69)=0),"",N(L69)/K69) -> 0.37204386
A70: Collar Fino Circulo | B70: Plata 925 | C70: Collar | D70: 925 ARG | E70: https://925arg.com/product.php?id=13722&iddet=19768 | F70: 17600 | H70: =IF($A70="","",$D$13) -> 1316.6403 | I70: =IF($A70="","",N(F70)*(1-N(G70))+N(H70)) -> 18916.64 | J70: =IF($A70="","",CEILING(I70*$B$18,500)) -> 38000 | K70: 28000 | L70: =IF(OR($A70="",N(K70)=0),"",K70-K70*$B$19-N(I70)) -> 9083.3597 | M70: =IF(OR($A70="",N(K70)=0),"",N(L70)/K70) -> 0.3244057
E71: https://925arg.com/product.php?id=13722&iddet=19768 | H71: =IF($A71="","",$D$13) | I71: =IF($A71="","",N(F71)*(1-N(G71))+N(H71)) | J71: =IF($A71="","",CEILING(I71*$B$18,500)) | L71: =IF(OR($A71="",N(K71)=0),"",K71-K71*$B$19-N(I71)) | M71: =IF(OR($A71="",N(K71)=0),"",N(L71)/K71)
A72: Anillo Cala | B72: Acero dorado | C72: Anillo | D72: Cata Jewels | E72: https://catajewelsmayorista.com/products/anillo-gildy?variant=53871300247920 | F72: 8424 | H72: =IF($A72="","",$D$13) -> 1316.6403 | I72: =IF($A72="","",N(F72)*(1-N(G72))+N(H72)) -> 9740.6403 | J72: =IF($A72="","",CEILING(I72*$B$18,500)) -> 19500 | K72: 18000 | L72: =IF(OR($A72="",N(K72)=0),"",K72-K72*$B$19-N(I72)) -> 8259.3597 | M72: =IF(OR($A72="",N(K72)=0),"",N(L72)/K72) -> 0.45885332
A73: Anillo Malvina Dorado | B73: Acero dorado | C73: Anillo | D73: Cata Jewels | E73: https://catajewelsmayorista.com/products/anillo-eden-gold?variant=53793671709040&sso=silent | F73: 3541 | H73: =IF($A73="","",$D$13) -> 1316.6403 | I73: =IF($A73="","",N(F73)*(1-N(G73))+N(H73)) -> 4857.6403 | J73: =IF($A73="","",CEILING(I73*$B$18,500)) -> 10000 | K73: 13000 | L73: =IF(OR($A73="",N(K73)=0),"",K73-K73*$B$19-N(I73)) -> 8142.3597 | M73: =IF(OR($A73="",N(K73)=0),"",N(L73)/K73) -> 0.62633536
A74: Anillo Malvina Plateado | B74: Acero inoxidable | C74: Anillo | D74: Cata Jewels | E74: https://catajewelsmayorista.com/products/anillo-eden-gold?variant=53793671709040&sso=silent | F74: 2603 | H74: =IF($A74="","",$D$13) -> 1316.6403 | I74: =IF($A74="","",N(F74)*(1-N(G74))+N(H74)) -> 3919.6403 | J74: =IF($A74="","",CEILING(I74*$B$18,500)) -> 8000 | K74: 13000 | L74: =IF(OR($A74="",N(K74)=0),"",K74-K74*$B$19-N(I74)) -> 9080.3597 | M74: =IF(OR($A74="",N(K74)=0),"",N(L74)/K74) -> 0.69848921
A75: Anillo Luna | B75: Acero inoxidable | C75: Anillo | D75: Cata Jewels | E75: https://catajewelsmayorista.com/products/anillo-poppy-silver?variant=52561699406192 | F75: 2877 | H75: =IF($A75="","",$D$13) -> 1316.6403 | I75: =IF($A75="","",N(F75)*(1-N(G75))+N(H75)) -> 4193.6403 | J75: =IF($A75="","",CEILING(I75*$B$18,500)) -> 8500 | K75: 12500 | L75: =IF(OR($A75="",N(K75)=0),"",K75-K75*$B$19-N(I75)) -> 8306.3597 | M75: =IF(OR($A75="",N(K75)=0),"",N(L75)/K75) -> 0.66450877
A76: Collar Girasol | B76: Acero dorado | C76: Collar | D76: Cata Jewels | E76: https://catajewelsmayorista.com/products/collar-el-girasol?variant=54184174354800 | F76: 9595 | H76: =IF($A76="","",$D$13) -> 1316.6403 | I76: =IF($A76="","",N(F76)*(1-N(G76))+N(H76)) -> 10911.64 | J76: =IF($A76="","",CEILING(I76*$B$18,500)) -> 22000 | K76: 24000 | L76: =IF(OR($A76="",N(K76)=0),"",K76-K76*$B$19-N(I76)) -> 13088.36 | M76: =IF(OR($A76="",N(K76)=0),"",N(L76)/K76) -> 0.54534832
A77: Collar Sardina | B77: Acero dorado | C77: Collar | D77: Cata Jewels | E77: https://catajewelsmayorista.com/products/collar-el-pez?variant=54184174387568&sso=silent | F77: 10425 | H77: =IF($A77="","",$D$13) -> 1316.6403 | I77: =IF($A77="","",N(F77)*(1-N(G77))+N(H77)) -> 11741.64 | J77: =IF($A77="","",CEILING(I77*$B$18,500)) -> 23500 | K77: 24000 | L77: =IF(OR($A77="",N(K77)=0),"",K77-K77*$B$19-N(I77)) -> 12258.36 | M77: =IF(OR($A77="",N(K77)=0),"",N(L77)/K77) -> 0.51076499
A78: Aros Atlas | B78: Acero dorado | C78: Aros | D78: Cata Jewels | E78: https://catajewelsmayorista.com/products/aros-boldie-gold | F78: 7648 | H78: =IF($A78="","",$D$13) -> 1316.6403 | I78: =IF($A78="","",N(F78)*(1-N(G78))+N(H78)) -> 8964.6403 | J78: =IF($A78="","",CEILING(I78*$B$18,500)) -> 18000 | K78: 16500 | L78: =IF(OR($A78="",N(K78)=0),"",K78-K78*$B$19-N(I78)) -> 7535.3597 | M78: =IF(OR($A78="",N(K78)=0),"",N(L78)/K78) -> 0.45668847
A79: Aros Rosella Dorado | B79: Acero dorado | C79: Aros | D79: Cata Jewels | E79: https://catajewelsmayorista.com/products/aros-rosella-gold?variant=52784303604080 | F79: 7282 | H79: =IF($A79="","",$D$13) -> 1316.6403 | I79: =IF($A79="","",N(F79)*(1-N(G79))+N(H79)) -> 8598.6403 | J79: =IF($A79="","",CEILING(I79*$B$18,500)) -> 17500 | K79: 15000 | L79: =IF(OR($A79="",N(K79)=0),"",K79-K79*$B$19-N(I79)) -> 6401.3597 | M79: =IF(OR($A79="",N(K79)=0),"",N(L79)/K79) -> 0.42675731
A80: Aros Nara | B80: Acero dorado | C80: Aros | D80: Cata Jewels | E80: https://catajewelsmayorista.com/products/aros-mediterraneo?variant=52784305668464 | F80: 5776 | H80: =IF($A80="","",$D$13) -> 1316.6403 | I80: =IF($A80="","",N(F80)*(1-N(G80))+N(H80)) -> 7092.6403 | J80: =IF($A80="","",CEILING(I80*$B$18,500)) -> 14500 | K80: 15000 | L80: =IF(OR($A80="",N(K80)=0),"",K80-K80*$B$19-N(I80)) -> 7907.3597 | M80: =IF(OR($A80="",N(K80)=0),"",N(L80)/K80) -> 0.52715731
A81: Aros Oliva | B81: Acero dorado | C81: Aros | D81: Cata Jewels | E81: https://catajewelsmayorista.com/products/aros-towers?variant=52784305045872 | F81: 5883 | H81: =IF($A81="","",$D$13) -> 1316.6403 | I81: =IF($A81="","",N(F81)*(1-N(G81))+N(H81)) -> 7199.6403 | J81: =IF($A81="","",CEILING(I81*$B$18,500)) -> 14500 | K81: 15000 | L81: =IF(OR($A81="",N(K81)=0),"",K81-K81*$B$19-N(I81)) -> 7800.3597 | M81: =IF(OR($A81="",N(K81)=0),"",N(L81)/K81) -> 0.52002398
A82: Collar Amour | B82: Acero inoxidable | C82: Collar | D82: Cata Jewels | E82: https://catajewelsmayorista.com/products/collar-marinero-silver-heart?variant=52721739399536 | F82: 5410 | H82: =IF($A82="","",$D$13) -> 1316.6403 | I82: =IF($A82="","",N(F82)*(1-N(G82))+N(H82)) -> 6726.6403 | J82: =IF($A82="","",CEILING(I82*$B$18,500)) -> 13500 | K82: 15000 | L82: =IF(OR($A82="",N(K82)=0),"",K82-K82*$B$19-N(I82)) -> 8273.3597 | M82: =IF(OR($A82="",N(K82)=0),"",N(L82)/K82) -> 0.55155731
A83: Argollitas Classic N°1 D | B83: Acero dorado | C83: Aros | D83: Cata Jewels | E83: https://catajewelsmayorista.com/products/collar-marinero-silver-heart?variant=52721739399536 | F83: 1707 | H83: =IF($A83="","",$D$13) -> 1316.6403 | I83: =IF($A83="","",N(F83)*(1-N(G83))+N(H83)) -> 3023.6403 | J83: =IF($A83="","",CEILING(I83*$B$18,500)) -> 6500 | K83: 9000 | L83: =IF(OR($A83="",N(K83)=0),"",K83-K83*$B$19-N(I83)) -> 5976.3597 | M83: =IF(OR($A83="",N(K83)=0),"",N(L83)/K83) -> 0.66403996
A84: Argollitas Classic N°2 D | B84: Acero dorado | C84: Aros | D84: Cata Jewels | F84: 1707 | H84: =IF($A84="","",$D$13) -> 1316.6403 | I84: =IF($A84="","",N(F84)*(1-N(G84))+N(H84)) -> 3023.6403 | J84: =IF($A84="","",CEILING(I84*$B$18,500)) -> 6500 | K84: 9000 | L84: =IF(OR($A84="",N(K84)=0),"",K84-K84*$B$19-N(I84)) -> 5976.3597 | M84: =IF(OR($A84="",N(K84)=0),"",N(L84)/K84) -> 0.66403996
D85: Cata Jewels | H85: =IF($A85="","",$D$13) | I85: =IF($A85="","",N(F85)*(1-N(G85))+N(H85)) | J85: =IF($A85="","",CEILING(I85*$B$18,500)) | K85: 10000 | L85: =IF(OR($A85="",N(K85)=0),"",K85-K85*$B$19-N(I85)) | M85: =IF(OR($A85="",N(K85)=0),"",N(L85)/K85)
H86: =IF($A86="","",$D$13) | I86: =IF($A86="","",N(F86)*(1-N(G86))+N(H86)) | J86: =IF($A86="","",CEILING(I86*$B$18,500)) | L86: =IF(OR($A86="",N(K86)=0),"",K86-K86*$B$19-N(I86)) | M86: =IF(OR($A86="",N(K86)=0),"",N(L86)/K86)
H87: =IF($A87="","",$D$13) | I87: =IF($A87="","",N(F87)*(1-N(G87))+N(H87)) | J87: =IF($A87="","",CEILING(I87*$B$18,500)) | L87: =IF(OR($A87="",N(K87)=0),"",K87-K87*$B$19-N(I87)) | M87: =IF(OR($A87="",N(K87)=0),"",N(L87)/K87)
A88: Argollitas Halo N°1 (12 mm) | B88: Plata 925 | C88: Aros | D88: 925 ARG | E88: https://925arg.com/product.php?id=29355&iddet=48085 | F88: 13750 | H88: =IF($A88="","",$D$13) -> 1316.6403 | I88: =IF($A88="","",N(F88)*(1-N(G88))+N(H88)) -> 15066.64 | J88: =IF($A88="","",CEILING(I88*$B$18,500)) -> 30500 | K88: 25000 | L88: =IF(OR($A88="",N(K88)=0),"",K88-K88*$B$19-N(I88)) -> 9933.3597 | M88: =IF(OR($A88="",N(K88)=0),"",N(L88)/K88) -> 0.39733439
A89: Anillo Vera | B89: Plata 925 | C89: Anillo | D89: 925 ARG | E89: https://925arg.com/product.php?id=19594&iddet=29783 | F89: 12100 | H89: =IF($A89="","",$D$13) -> 1316.6403 | I89: =IF($A89="","",N(F89)*(1-N(G89))+N(H89)) -> 13416.64 | J89: =IF($A89="","",CEILING(I89*$B$18,500)) -> 27000 | K89: 22500 | L89: =IF(OR($A89="",N(K89)=0),"",K89-K89*$B$19-N(I89)) -> 9083.3597 | M89: =IF(OR($A89="",N(K89)=0),"",N(L89)/K89) -> 0.40370487
A90: Cubic Circulo (5mm) | B90: Plata 925 | C90: Aros | D90: 925 ARG | E90: https://925arg.com/product.php?id=6867&iddet=8612 | F90: 8800 | H90: =IF($A90="","",$D$13) -> 1316.6403 | I90: =IF($A90="","",N(F90)*(1-N(G90))+N(H90)) -> 10116.64 | J90: =IF($A90="","",CEILING(I90*$B$18,500)) -> 20500 | K90: 17500 | L90: =IF(OR($A90="",N(K90)=0),"",K90-K90*$B$19-N(I90)) -> 7383.3597 | M90: =IF(OR($A90="",N(K90)=0),"",N(L90)/K90) -> 0.42190627
A91: Aritos Perlas (4mm) | B91: Plata 925 | C91: Aros | D91: 925 ARG | E91: https://925arg.com/product.php?id=28569&iddet=44953 | F91: 4500 | H91: =IF($A91="","",$D$13) -> 1316.6403 | I91: =IF($A91="","",N(F91)*(1-N(G91))+N(H91)) -> 5816.6403 | J91: =IF($A91="","",CEILING(I91*$B$18,500)) -> 12000 | K91: 12000 | L91: =IF(OR($A91="",N(K91)=0),"",K91-K91*$B$19-N(I91)) -> 6183.3597 | M91: =IF(OR($A91="",N(K91)=0),"",N(L91)/K91) -> 0.51527997
A92: Argollitas Marco (10mm) | B92: Plata 925 | C92: Aros | D92: 925 ARG | E92: https://925arg.com/product.php?id=19170&iddet=28984 | F92: 20200 | H92: =IF($A92="","",$D$13) -> 1316.6403 | I92: =IF($A92="","",N(F92)*(1-N(G92))+N(H92)) -> 21516.64 | J92: =IF($A92="","",CEILING(I92*$B$18,500)) -> 43500 | K92: 32000 | L92: =IF(OR($A92="",N(K92)=0),"",K92-K92*$B$19-N(I92)) -> 10483.36 | M92: =IF(OR($A92="",N(K92)=0),"",N(L92)/K92) -> 0.32760499
A93: Argollitas Espiga (15mm) | B93: Plata 925 | C93: Aros | D93: 925 ARG | E93: https://925arg.com/product.php?id=19170&iddet=28984 | F93: 24000 | H93: =IF($A93="","",$D$13) -> 1316.6403 | I93: =IF($A93="","",N(F93)*(1-N(G93))+N(H93)) -> 25316.64 | J93: =IF($A93="","",CEILING(I93*$B$18,500)) -> 51000 | K93: 35000 | L93: =IF(OR($A93="",N(K93)=0),"",K93-K93*$B$19-N(I93)) -> 9683.3597 | M93: =IF(OR($A93="",N(K93)=0),"",N(L93)/K93) -> 0.27666742
A94: Aritos Corazón | B94: Plata 925 | C94: Aros | D94: 925 ARG | E94: https://925arg.com/product.php?id=46606&iddet=76912 combo | F94: 6900 | H94: =IF($A94="","",$D$13) -> 1316.6403 | I94: =IF($A94="","",N(F94)*(1-N(G94))+N(H94)) -> 8216.6403 | J94: =IF($A94="","",CEILING(I94*$B$18,500)) -> 16500 | K94: 14000 | L94: =IF(OR($A94="",N(K94)=0),"",K94-K94*$B$19-N(I94)) -> 5783.3597 | M94: =IF(OR($A94="",N(K94)=0),"",N(L94)/K94) -> 0.41309712
A95: Collar Aimee | B95: Plata 925 | C95: Collar | D95: 925 ARG | E95: https://925arg.com/product.php?id=46606&iddet=76912 combo | F95: 16000 | H95: =IF($A95="","",$D$13) -> 1316.6403 | I95: =IF($A95="","",N(F95)*(1-N(G95))+N(H95)) -> 17316.64 | J95: =IF($A95="","",CEILING(I95*$B$18,500)) -> 35000 | K95: 28000 | L95: =IF(OR($A95="",N(K95)=0),"",K95-K95*$B$19-N(I95)) -> 10683.36 | M95: =IF(OR($A95="",N(K95)=0),"",N(L95)/K95) -> 0.38154856
E96: https://925arg.com/product.php?id=46606&iddet=76912 | H96: =IF($A96="","",$D$13) | I96: =IF($A96="","",N(F96)*(1-N(G96))+N(H96)) | J96: =IF($A96="","",CEILING(I96*$B$18,500)) | L96: =IF(OR($A96="",N(K96)=0),"",K96-K96*$B$19-N(I96)) | M96: =IF(OR($A96="",N(K96)=0),"",N(L96)/K96)
H97: =IF($A97="","",$D$13) | I97: =IF($A97="","",N(F97)*(1-N(G97))+N(H97)) | J97: =IF($A97="","",CEILING(I97*$B$18,500)) | L97: =IF(OR($A97="",N(K97)=0),"",K97-K97*$B$19-N(I97)) | M97: =IF(OR($A97="",N(K97)=0),"",N(L97)/K97)
A98: Collar Delta | B98: Boho Colection | C98: Collar | D98: Utopias | E98: Alma Bohemia (dije triangular, collar piedras) 7032 | F98: 16500 | H98: =IF($A98="","",$D$13) -> 1316.6403 | I98: =IF($A98="","",N(F98)*(1-N(G98))+N(H98)) -> 17816.64 | J98: =IF($A98="","",CEILING(I98*$B$18,500)) -> 36000 | K98: 30000 | L98: =IF(OR($A98="",N(K98)=0),"",K98-K98*$B$19-N(I98)) -> 12183.36 | M98: =IF(OR($A98="",N(K98)=0),"",N(L98)/K98) -> 0.40611199
A99: Collar Bruna | B99: Boho Colection | C99: Collar | D99: Utopias | E99: Alma Bohemia (dije corazón, canutullido dorado y negro) 7033 | F99: 7000 | H99: =IF($A99="","",$D$13) -> 1316.6403 | I99: =IF($A99="","",N(F99)*(1-N(G99))+N(H99)) -> 8316.6403 | J99: =IF($A99="","",CEILING(I99*$B$18,500)) -> 17000 | K99: 18000 | L99: =IF(OR($A99="",N(K99)=0),"",K99-K99*$B$19-N(I99)) -> 9683.3597 | M99: =IF(OR($A99="",N(K99)=0),"",N(L99)/K99) -> 0.53796443
A100: Collar Nova | B100: Boho Colection | C100: Collar | D100: Utopias | E100: Alma Bohemia (dije estrella, cuero marron cadena) 7034 | F100: 13400 | H100: =IF($A100="","",$D$13) -> 1316.6403 | I100: =IF($A100="","",N(F100)*(1-N(G100))+N(H100)) -> 14716.64 | J100: =IF($A100="","",CEILING(I100*$B$18,500)) -> 29500 | K100: 28000 | L100: =IF(OR($A100="",N(K100)=0),"",K100-K100*$B$19-N(I100)) -> 13283.36 | M100: =IF(OR($A100="",N(K100)=0),"",N(L100)/K100) -> 0.4744057
A101: Collar Luna | B101: Boho Colection | C101: Collar | D101: Utopias | E101: Alma Bohemia (dije luna, cadena pelotitas dorada) 7035 | F101: 18000 | H101: =IF($A101="","",$D$13) -> 1316.6403 | I101: =IF($A101="","",N(F101)*(1-N(G101))+N(H101)) -> 19316.64 | J101: =IF($A101="","",CEILING(I101*$B$18,500)) -> 39000 | K101: 32500 | L101: =IF(OR($A101="",N(K101)=0),"",K101-K101*$B$19-N(I101)) -> 13183.36 | M101: =IF(OR($A101="",N(K101)=0),"",N(L101)/K101) -> 0.40564184
A102: Collar Ambar | B102: Boho Colection | C102: Collar | D102: Utopias | E102: Alma Bohemia (muchos dijes, cadena cuero mini marrón) 7036 | F102: 13200 | H102: =IF($A102="","",$D$13) -> 1316.6403 | I102: =IF($A102="","",N(F102)*(1-N(G102))+N(H102)) -> 14516.64 | J102: =IF($A102="","",CEILING(I102*$B$18,500)) -> 29500 | K102: 26500 | L102: =IF(OR($A102="",N(K102)=0),"",K102-K102*$B$19-N(I102)) -> 11983.36 | M102: =IF(OR($A102="",N(K102)=0),"",N(L102)/K102) -> 0.45220225
A103: Pulsera Bruna | B103: Boho Colection | C103: Pulsera | D103: Utopias | E103: Alma Bohemia (pulsera canutillo dorado y negro) 7038 | F103: 3600 | H103: =IF($A103="","",$D$13) -> 1316.6403 | I103: =IF($A103="","",N(F103)*(1-N(G103))+N(H103)) -> 4916.6403 | J103: =IF($A103="","",CEILING(I103*$B$18,500)) -> 10000 | K103: 9000 | L103: =IF(OR($A103="",N(K103)=0),"",K103-K103*$B$19-N(I103)) -> 4083.3597 | M103: =IF(OR($A103="",N(K103)=0),"",N(L103)/K103) -> 0.45370663
A104: Collar Nina | B104: Boho Colection | C104: Collar | D104: Utopias | E104: Alma Bohemia (collar canutillo con campanitas) 7040 | F104: 6000 | H104: =IF($A104="","",$D$13) -> 1316.6403 | I104: =IF($A104="","",N(F104)*(1-N(G104))+N(H104)) -> 7316.6403 | J104: =IF($A104="","",CEILING(I104*$B$18,500)) -> 15000 | K104: 16000 | L104: =IF(OR($A104="",N(K104)=0),"",K104-K104*$B$19-N(I104)) -> 8683.3597 | M104: =IF(OR($A104="",N(K104)=0),"",N(L104)/K104) -> 0.54270998
A105: Collar Duna | B105: Boho Colection | C105: Collar | D105: Utopias | E105: Alma Bohemia (collar canutillo con diente crudo) 7048 | F105: 8000 | H105: =IF($A105="","",$D$13) -> 1316.6403 | I105: =IF($A105="","",N(F105)*(1-N(G105))+N(H105)) -> 9316.6403 | J105: =IF($A105="","",CEILING(I105*$B$18,500)) -> 19000 | K105: 18500 | L105: =IF(OR($A105="",N(K105)=0),"",K105-K105*$B$19-N(I105)) -> 9183.3597 | M105: =IF(OR($A105="",N(K105)=0),"",N(L105)/K105) -> 0.49639782
...

Sheet Compras
A1: COMPRAS
A2: Una línea por cada pieza que comprás. Elegí el producto de la lista y poné el talle solo si es anillo.
A3: Dejá el costo vacío para que tome el costo total de la hoja Costos. Escribilo solo si pagaste otro precio.
A5: Fecha | B5: Producto | C5: Talle | D5: Cantidad | E5: Costo unitario | F5: Total | G5: Proveedor / Notas
A6: 46244 | B6: Argollitas Classic N°1 | C6: Único | D6: 1 | F6: =IF($B6="","",N($D6)*IF(N($E6)>0,$E6,IFERROR(INDEX(Costos!$I$23:$I$300,MATCH($B6,Costos!$A$23:$A$300,0)),0))) -> 3877.1403 | G6: Stock inicial
A7: 46244 | B7: Argollitas Classic N°2 | C7: Único | D7: 1 | F7: =IF($B7="","",N($D7)*IF(N($E7)>0,$E7,IFERROR(INDEX(Costos!$I$23:$I$300,MATCH($B7,Costos!$A$23:$A$300,0)),0))) -> 4381.1403 | G7: Stock inicial
A8: 46244 | B8: Argollitas Classic N°3 | C8: Único | D8: 1 | F8: =IF($B8="","",N($D8)*IF(N($E8)>0,$E8,IFERROR(INDEX(Costos!$I$23:$I$300,MATCH($B8,Costos!$A$23:$A$300,0)),0))) -> 4885.1403 | G8: Stock inicial
A9: 46244 | B9: Argollitas Classic N°4 | C9: Único | D9: 1 | F9: =IF($B9="","",N($D9)*IF(N($E9)>0,$E9,IFERROR(INDEX(Costos!$I$23:$I$300,MATCH($B9,Costos!$A$23:$A$300,0)),0))) -> 5389.1403 | G9: Stock inicial
A10: 46244 | B10: Argollitas Classic N°5 | C10: Único | D10: 2 | F10: =IF($B10="","",N($D10)*IF(N($E10)>0,$E10,IFERROR(INDEX(Costos!$I$23:$I$300,MATCH($B10,Costos!$A$23:$A$300,0)),0))) -> 11282.281 | G10: Stock inicial
A11: 46244 | B11: Cubic Mini Circulo | C11: Único | D11: 1 | F11: =IF($B11="","",N($D11)*IF(N($E11)>0,$E11,IFERROR(INDEX(Costos!$I$23:$I$300,MATCH($B11,Costos!$A$23:$A$300,0)),0))) -> 7076.6403 | G11: Stock inicial
A12: 46244 | B12: Cubic Circulo Docha | C12: Único | D12: 1 | F12: =IF($B12="","",N($D12)*IF(N($E12)>0,$E12,IFERROR(INDEX(Costos!$I$23:$I$300,MATCH($B12,Costos!$A$23:$A$300,0)),0))) -> 7436.6403 | G12: Stock inicial
A13: 46244 | B13: Cubic Cuadrado | C13: Único | D13: 1 | F13: =IF($B13="","",N($D13)*IF(N($E13)>0,$E13,IFERROR(INDEX(Costos!$I$23:$I$300,MATCH($B13,Costos!$A$23:$A$300,0)),0))) -> 6959.6403 | G13: Stock inicial
A14: 46244 | B14: Argollitas Marco Docha | C14: Único | D14: 1 | F14: =IF($B14="","",N($D14)*IF(N($E14)>0,$E14,IFERROR(INDEX(Costos!$I$23:$I$300,MATCH($B14,Costos!$A$23:$A$300,0)),0))) -> 18097.14 | G14: Stock inicial
A15: 46244 | B15: Anillo Sin Fin | C15: Mediano | D15: 1 | F15: =IF($B15="","",N($D15)*IF(N($E15)>0,$E15,IFERROR(INDEX(Costos!$I$23:$I$300,MATCH($B15,Costos!$A$23:$A$300,0)),0))) -> 12916.64 | G15: Stock inicial
A16: 46244 | B16: Anillo Circulo | C16: Chico | D16: 1 | F16: =IF($B16="","",N($D16)*IF(N($E16)>0,$E16,IFERROR(INDEX(Costos!$I$23:$I$300,MATCH($B16,Costos!$A$23:$A$300,0)),0))) -> 8741.6403 | G16: Stock inicial
A17: 46244 | B17: Anillo Circulo | C17: Mediano | D17: 1 | F17: =IF($B17="","",N($D17)*IF(N($E17)>0,$E17,IFERROR(INDEX(Costos!$I$23:$I$300,MATCH($B17,Costos!$A$23:$A$300,0)),0))) -> 8741.6403 | G17: Stock inicial
... A31: 46248 | B31: Anillo Corazón I | C31: Único | D31: 1 | F31: =IF($B31="","",N($D31)*IF(N($E31)>0,$E31,IFERROR(INDEX(Costos!$I$23:$I$300,MATCH($B31,Costos!$A$23:$A$300,0)),0))) -> 7816.6403 | G31: stock inicial
A32: 46248 | B32: Anillo Ovalo | C32: Único | D32: 1 | F32: =IF($B32="","",N($D32)*IF(N($E32)>0,$E32,IFERROR(INDEX(Costos!$I$23:$I$300,MATCH($B32,Costos!$A$23:$A$300,0)),0))) -> 5816.6403
A33: 46248 | B33: Anillo Star | C33: Único | D33: 1 | F33: =IF($B33="","",N($D33)*IF(N($E33)>0,$E33,IFERROR(INDEX(Costos!$I$23:$I$300,MATCH($B33,Costos!$A$23:$A$300,0)),0))) -> 5816.6403
A34: 46248 | B34: Anillo Nodo | C34: Único | D34: 2 | F34: =IF($B34="","",N($D34)*IF(N($E34)>0,$E34,IFERROR(INDEX(Costos!$I$23:$I$300,MATCH($B34,Costos!$A$23:$A$300,0)),0))) -> 15633.281
A35: 46248 | B35: Anillo Corazón II Plateado | C35: Único | D35: 2 | F35: =IF($B35="","",N($D35)*IF(N($E35)>0,$E35,IFERROR(INDEX(Costos!$I$23:$I$300,MATCH($B35,Costos!$A$23:$A$300,0)),0))) -> 13633.281
A36: 46248 | B36: Anillo Irregular | C36: Único | D36: 2 | F36: =IF($B36="","",N($D36)*IF(N($E36)>0,$E36,IFERROR(INDEX(Costos!$I$23:$I$300,MATCH($B36,Costos!$A$23:$A$300,0)),0))) -> 11633.281
A37: 46248 | B37: Anillo Zafira | C37: Único | D37: 2 | F37: =IF($B37="","",N($D37)*IF(N($E37)>0,$E37,IFERROR(INDEX(Costos!$I$23:$I$300,MATCH($B37,Costos!$A$23:$A$300,0)),0))) -> 15633.281
A38: 46248 | B38: Anillo Norix | C38: Único | D38: 2 | F38: =IF($B38="","",N($D38)*IF(N($E38)>0,$E38,IFERROR(INDEX(Costos!$I$23:$I$300,MATCH($B38,Costos!$A$23:$A$300,0)),0))) -> 11633.281
A39: 46249 | B39: Anillo Vanton | C39: Único | D39: 2 | F39: =IF($B39="","",N($D39)*IF(N($E39)>0,$E39,IFERROR(INDEX(Costos!$I$23:$I$300,MATCH($B39,Costos!$A$23:$A$300,0)),0))) -> 11633.281
A40: 46250 | B40: Anillo Azmira | C40: Único | D40: 1 | F40: =IF($B40="","",N($D40)*IF(N($E40)>0,$E40,IFERROR(INDEX(Costos!$I$23:$I$300,MATCH($B40,Costos!$A$23:$A$300,0)),0))) -> 5816.6403
A41: 46251 | B41: Anillo Mina | C41: Único | D41: 2 | F41: =IF($B41="","",N($D41)*IF(N($E41)>0,$E41,IFERROR(INDEX(Costos!$I$23:$I$300,MATCH($B41,Costos!$A$23:$A$300,0)),0))) -> 15633.281
A42: 46251 | B42: Anillo Virel | C42: Único | D42: 2 | F42: =IF($B42="","",N($D42)*IF(N($E42)>0,$E42,IFERROR(INDEX(Costos!$I$23:$I$300,MATCH($B42,Costos!$A$23:$A$300,0)),0))) -> 13633.281
A43: 46244 | B43: Argollitas Bubble | C43: Único | D43: 1 | F43: =IF($B43="","",N($D43)*IF(N($E43)>0,$E43,IFERROR(INDEX(Costos!$I$23:$I$300,MATCH($B43,Costos!$A$23:$A$300,0)),0))) -> 4106.6403
F44: =IF($B44="","",N($D44)*IF(N($E44)>0,$E44,IFERROR(INDEX(Costos!$I$23:$I$300,MATCH($B44,Costos!$A$23:$A$300,0)),0)))
A45: 46258 | B45: Cubic Mini cuadrado | C45: Único | D45: 2 | F45: =IF($B45="","",N($D45)*IF(N($E45)>0,$E45,IFERROR(INDEX(Costos!$I$23:$I$300,MATCH($B45,Costos!$A$23:$A$300,0)),0))) -> 9733.2807
A46: 46258 | B46: Aros Halo N°2 (14 mm) | C46: Único | D46: 2 | F46: =IF($B46="","",N($D46)*IF(N($E46)>0,$E46,IFERROR(INDEX(Costos!$I$23:$I$300,MATCH($B46,Costos!$A$23:$A$300,0)),0))) -> 29633.281
A47: 46258 | B47: Aros Gala (12 mm) | C47: Único | D47: 1 | F47: =IF($B47="","",N($D47)*IF(N($E47)>0,$E47,IFERROR(INDEX(Costos!$I$23:$I$300,MATCH($B47,Costos!$A$23:$A$300,0)),0))) -> 16866.64
A48: 46258 | B48: Argollitas 10mm | C48: Único | D48: 2 | F48: =IF($B48="","",N($D48)*IF(N($E48)>0,$E48,IFERROR(INDEX(Costos!$I$23:$I$300,MATCH($B48,Costos!$A$23:$A$300,0)),0))) -> 6533.2807
A49: 46258 | B49: Anillos Corazones III | C49: Único | D49: 1 | F49: =IF($B49="","",N($D49)*IF(N($E49)>0,$E49,IFERROR(INDEX(Costos!$I$23:$I$300,MATCH($B49,Costos!$A$23:$A$300,0)),0))) -> 15066.64
A50: 46258 | B50: Anillo Vena | C50: Único | D50: 1 | F50: =IF($B50="","",N($D50)*IF(N($E50)>0,$E50,IFERROR(INDEX(Costos!$I$23:$I$300,MATCH($B50,Costos!$A$23:$A$300,0)),0))) -> 16716.64
A51: 46258 | B51: Anillo Deriva | C51: Único | D51: 1 | F51: =IF($B51="","",N($D51)*IF(N($E51)>0,$E51,IFERROR(INDEX(Costos!$I$23:$I$300,MATCH($B51,Costos!$A$23:$A$300,0)),0))) -> 18266.64
A52: 46258 | B52: Collar Muna Circulo | C52: Único | D52: 1 | F52: =IF($B52="","",N($D52)*IF(N($E52)>0,$E52,IFERROR(INDEX(Costos!$I$23:$I$300,MATCH($B52,Costos!$A$23:$A$300,0)),0))) -> 18566.64
A53: 46258 | B53: Collar Muna Corazón | C53: Único | D53: 1 | F53: =IF($B53="","",N($D53)*IF(N($E53)>0,$E53,IFERROR(INDEX(Costos!$I$23:$I$300,MATCH($B53,Costos!$A$23:$A$300,0)),0))) -> 19466.64
A54: 46258 | B54: Collar Fino Circulo | C54: Único | D54: 1 | F54: =IF($B54="","",N($D54)*IF(N($E54)>0,$E54,IFERROR(INDEX(Costos!$I$23:$I$300,MATCH($B54,Costos!$A$23:$A$300,0)),0))) -> 18916.64
A55: 46258 | B55: Anillo Sin Fin | C55: Mediano | D55: 2 | F55: =IF($B55="","",N($D55)*IF(N($E55)>0,$E55,IFERROR(INDEX(Costos!$I$23:$I$300,MATCH($B55,Costos!$A$23:$A$300,0)),0))) -> 25833.281
F56: =IF($B56="","",N($D56)*IF(N($E56)>0,$E56,IFERROR(INDEX(Costos!$I$23:$I$300,MATCH($B56,Costos!$A$23:$A$300,0)),0)))
A57: 46262 | B57: Anillo Cala | C57: Chico | D57: 1 | F57: =IF($B57="","",N($D57)*IF(N($E57)>0,$E57,IFERROR(INDEX(Costos!$I$23:$I$300,MATCH($B57,Costos!$A$23:$A$300,0)),0))) -> 9740.6403
A58: 46262 | B58: Anillo Cala | C58: Mediano | D58: 1 | F58: =IF($B58="","",N($D58)*IF(N($E58)>0,$E58,IFERROR(INDEX(Costos!$I$23:$I$300,MATCH($B58,Costos!$A$23:$A$300,0)),0))) -> 9740.6403
A59: 46262 | B59: Anillo Malvina Dorado | C59: Único | D59: 3 | F59: =IF($B59="","",N($D59)*IF(N($E59)>0,$E59,IFERROR(INDEX(Costos!$I$23:$I$300,MATCH($B59,Costos!$A$23:$A$300,0)),0))) -> 14572.921
A60: 46262 | B60: Anillo Malvina Plateado | C60: Único | D60: 2 | F60: =IF($B60="","",N($D60)*IF(N($E60)>0,$E60,IFERROR(INDEX(Costos!$I$23:$I$300,MATCH($B60,Costos!$A$23:$A$300,0)),0))) -> 7839.2807
A61: 46262 | B61: Anillo Luna | C61: Único | D61: 2 | F61: =IF($B61="","",N($D61)*IF(N($E61)>0,$E61,IFERROR(INDEX(Costos!$I$23:$I$300,MATCH($B61,Costos!$A$23:$A$300,0)),0))) -> 8387.2807
A62: 46262 | B62: Collar Girasol | C62: Único | D62: 1 | F62: =IF($B62="","",N($D62)*IF(N($E62)>0,$E62,IFERROR(INDEX(Costos!$I$23:$I$300,MATCH($B62,Costos!$A$23:$A$300,0)),0))) -> 10911.64
A63: 46262 | B63: Collar Sardina | C63: Único | D63: 1 | F63: =IF($B63="","",N($D63)*IF(N($E63)>0,$E63,IFERROR(INDEX(Costos!$I$23:$I$300,MATCH($B63,Costos!$A$23:$A$300,0)),0))) -> 11741.64
A64: 46262 | B64: Aros Atlas | C64: Único | D64: 1 | F64: =IF($B64="","",N($D64)*IF(N($E64)>0,$E64,IFERROR(INDEX(Costos!$I$23:$I$300,MATCH($B64,Costos!$A$23:$A$300,0)),0))) -> 8964.6403
A65: 46262 | B65: Aros Rosella Dorado | C65: Único | D65: 1 | F65: =IF($B65="","",N($D65)*IF(N($E65)>0,$E65,IFERROR(INDEX(Costos!$I$23:$I$300,MATCH($B65,Costos!$A$23:$A$300,0)),0))) -> 8598.6403
A66: 46262 | B66: Aros Nara | C66: Único | D66: 1 | F66: =IF($B66="","",N($D66)*IF(N($E66)>0,$E66,IFERROR(INDEX(Costos!$I$23:$I$300,MATCH($B66,Costos!$A$23:$A$300,0)),0))) -> 7092.6403
A67: 46262 | B67: Aros Oliva | C67: Único | D67: 1 | F67: =IF($B67="","",N($D67)*IF(N($E67)>0,$E67,IFERROR(INDEX(Costos!$I$23:$I$300,MATCH($B67,Costos!$A$23:$A$300,0)),0))) -> 7199.6403
A68: 46262 | B68: Collar Amour | C68: Único | D68: 2 | F68: =IF($B68="","",N($D68)*IF(N($E68)>0,$E68,IFERROR(INDEX(Costos!$I$23:$I$300,MATCH($B68,Costos!$A$23:$A$300,0)),0))) -> 13453.281
... A70: 46262 | B70: Argollitas Classic N°2 D | C70: Único | D70: 2 | F70: =IF($B70="","",N($D70)*IF(N($E70)>0,$E70,IFERROR(INDEX(Costos!$I$23:$I$300,MATCH($B70,Costos!$A$23:$A$300,0)),0))) -> 6047.2807
F71: =IF($B71="","",N($D71)*IF(N($E71)>0,$E71,IFERROR(INDEX(Costos!$I$23:$I$300,MATCH($B71,Costos!$A$23:$A$300,0)),0)))
A72: 46268 | B72: Argollitas Halo N°1 (12 mm) | C72: Único | D72: 2 | F72: =IF($B72="","",N($D72)*IF(N($E72)>0,$E72,IFERROR(INDEX(Costos!$I$23:$I$300,MATCH($B72,Costos!$A$23:$A$300,0)),0))) -> 30133.281
A73: 46268 | B73: Anillos Corazones III | C73: Único | D73: 2 | F73: =IF($B73="","",N($D73)*IF(N($E73)>0,$E73,IFERROR(INDEX(Costos!$I$23:$I$300,MATCH($B73,Costos!$A$23:$A$300,0)),0))) -> 30133.281
A74: 46268 | B74: Anillo Vera | C74: Mediano | D74: 2 | F74: =IF($B74="","",N($D74)*IF(N($E74)>0,$E74,IFERROR(INDEX(Costos!$I$23:$I$300,MATCH($B74,Costos!$A$23:$A$300,0)),0))) -> 26833.281
A75: 46268 | B75: Anillo Vera | C75: Grande | D75: 1 | F75: =IF($B75="","",N($D75)*IF(N($E75)>0,$E75,IFERROR(INDEX(Costos!$I$23:$I$300,MATCH($B75,Costos!$A$23:$A$300,0)),0))) -> 13416.64
A76: 46268 | B76: Collar Muna Corazón | C76: Único | D76: 1 | F76: =IF($B76="","",N($D76)*IF(N($E76)>0,$E76,IFERROR(INDEX(Costos!$I$23:$I$300,MATCH($B76,Costos!$A$23:$A$300,0)),0))) -> 19466.64
A77: 46268 | B77: Collar Muna Circulo | C77: Único | D77: 1 | F77: =IF($B77="","",N($D77)*IF(N($E77)>0,$E77,IFERROR(INDEX(Costos!$I$23:$I$300,MATCH($B77,Costos!$A$23:$A$300,0)),0))) -> 18566.64
A78: 46268 | B78: Anillo Sin Fin | C78: Mediano | D78: 3 | F78: =IF($B78="","",N($D78)*IF(N($E78)>0,$E78,IFERROR(INDEX(Costos!$I$23:$I$300,MATCH($B78,Costos!$A$23:$A$300,0)),0))) -> 38749.921
A79: 46268 | B79: Cubic Circulo (5mm) | C79: Único | D79: 2 | F79: =IF($B79="","",N($D79)*IF(N($E79)>0,$E79,IFERROR(INDEX(Costos!$I$23:$I$300,MATCH($B79,Costos!$A$23:$A$300,0)),0))) -> 20233.281
A80: 46268 | B80: Aritos Perlas (4mm) | C80: Único | D80: 2 | F80: =IF($B80="","",N($D80)*IF(N($E80)>0,$E80,IFERROR(INDEX(Costos!$I$23:$I$300,MATCH($B80,Costos!$A$23:$A$300,0)),0))) -> 11633.281
A81: 46268 | B81: Argollitas Espiga (15mm) | C81: Único | D81: 1 | F81: =IF($B81="","",N($D81)*IF(N($E81)>0,$E81,IFERROR(INDEX(Costos!$I$23:$I$300,MATCH($B81,Costos!$A$23:$A$300,0)),0))) -> 25316.64
A82: 46268 | B82: Collar Aimee | C82: Único | D82: 1 | F82: =IF($B82="","",N($D82)*IF(N($E82)>0,$E82,IFERROR(INDEX(Costos!$I$23:$I$300,MATCH($B82,Costos!$A$23:$A$300,0)),0))) -> 17316.64
A83: 46268 | B83: Aritos Corazón | C83: Único | D83: 1 | F83: =IF($B83="","",N($D83)*IF(N($E83)>0,$E83,IFERROR(INDEX(Costos!$I$23:$I$300,MATCH($B83,Costos!$A$23:$A$300,0)),0))) -> 8216.6403
F84: =IF($B84="","",N($D84)*IF(N($E84)>0,$E84,IFERROR(INDEX(Costos!$I$23:$I$300,MATCH($B84,Costos!$A$23:$A$300,0)),0)))
A85: 46272 | B85: Collar Delta | C85: Único | D85: 1 | F85: =IF($B85="","",N($D85)*IF(N($E85)>0,$E85,IFERROR(INDEX(Costos!$I$23:$I$300,MATCH($B85,Costos!$A$23:$A$300,0)),0))) -> 17816.64
A86: 46272 | B86: Collar Bruna | C86: Único | D86: 1 | F86: =IF($B86="","",N($D86)*IF(N($E86)>0,$E86,IFERROR(INDEX(Costos!$I$23:$I$300,MATCH($B86,Costos!$A$23:$A$300,0)),0))) -> 8316.6403
A87: 46272 | B87: Collar Nova | C87: Único | D87: 1 | F87: =IF($B87="","",N($D87)*IF(N($E87)>0,$E87,IFERROR(INDEX(Costos!$I$23:$I$300,MATCH($B87,Costos!$A$23:$A$300,0)),0))) -> 14716.64
A88: 46272 | B88: Collar Luna | C88: Único | D88: 1 | F88: =IF($B88="","",N($D88)*IF(N($E88)>0,$E88,IFERROR(INDEX(Costos!$I$23:$I$300,MATCH($B88,Costos!$A$23:$A$300,0)),0))) -> 19316.64
A89: 46272 | B89: Collar Ambar | C89: Único | D89: 1 | F89: =IF($B89="","",N($D89)*IF(N($E89)>0,$E89,IFERROR(INDEX(Costos!$I$23:$I$300,MATCH($B89,Costos!$A$23:$A$300,0)),0))) -> 14516.64
A90: 46272 | B90: Pulsera Bruna | C90: Único | D90: 4 | F90: =IF($B90="","",N($D90)*IF(N($E90)>0,$E90,IFERROR(INDEX(Costos!$I$23:$I$300,MATCH($B90,Costos!$A$23:$A$300,0)),0))) -> 19666.561
A91: 46272 | B91: Collar Nina | C91: Único | D91: 1 | F91: =IF($B91="","",N($D91)*IF(N($E91)>0,$E91,IFERROR(INDEX(Costos!$I$23:$I$300,MATCH($B91,Costos!$A$23:$A$300,0)),0))) -> 7316.6403
A92: 46272 | B92: Collar Duna | C92: Único | D92: 1 | F92: =IF($B92="","",N($D92)*IF(N($E92)>0,$E92,IFERROR(INDEX(Costos!$I$23:$I$300,MATCH($B92,Costos!$A$23:$A$300,0)),0))) -> 9316.6403
A93: 46272 | B93: Collar Pampa | C93: Único | D93: 1 | F93: =IF($B93="","",N($D93)*IF(N($E93)>0,$E93,IFERROR(INDEX(Costos!$I$23:$I$300,MATCH($B93,Costos!$A$23:$A$300,0)),0))) -> 16116.64
A94: 46272 | B94: Collar Kaya | C94: Único | D94: 1 | F94: =IF($B94="","",N($D94)*IF(N($E94)>0,$E94,IFERROR(INDEX(Costos!$I$23:$I$300,MATCH($B94,Costos!$A$23:$A$300,0)),0))) -> 11116.64
A95: 46272 | B95: Collar Isla | C95: Único | D95: 1 | F95: =IF($B95="","",N($D95)*IF(N($E95)>0,$E95,IFERROR(INDEX(Costos!$I$23:$I$300,MATCH($B95,Costos!$A$23:$A$300,0)),0))) -> 13716.64
A96: 46272 | B96: Collar Vega | C96: Único | D96: 1 | F96: =IF($B96="","",N($D96)*IF(N($E96)>0,$E96,IFERROR(INDEX(Costos!$I$23:$I$300,MATCH($B96,Costos!$A$23:$A$300,0)),0))) -> 17816.64
... A102: 46272 | B102: Collar Arena | C102: Único | D102: 1 | F102: =IF($B102="","",N($D102)*IF(N($E102)>0,$E102,IFERROR(INDEX(Costos!$I$23:$I$300,MATCH($B102,Costos!$A$23:$A$300,0)),0))) -> 6516.6403
F103: =IF($B103="","",N($D103)*IF(N($E103)>0,$E103,IFERROR(INDEX(Costos!$I$23:$I$300,MATCH($B103,Costos!$A$23:$A$300,0)),0)))
F104: =IF($B104="","",N($D104)*IF(N($E104)>0,$E104,IFERROR(INDEX(Costos!$I$23:$I$300,MATCH($B104,Costos!$A$23:$A$300,0)),0)))
A105: 46272 | B105: Aros Rosella Dorado | C105: Único | D105: 2 | F105: =IF($B105="","",N($D105)*IF(N($E105)>0,$E105,IFERROR(INDEX(Costos!$I$23:$I$300,MATCH($B105,Costos!$A$23:$A$300,0)),0))) -> 17197.281
A106: 46272 | B106: Aros Atlas | C106: Único | D106: 2 | F106: =IF($B106="","",N($D106)*IF(N($E106)>0,$E106,IFERROR(INDEX(Costos!$I$23:$I$300,MATCH($B106,Costos!$A$23:$A$300,0)),0))) -> 17929.281
A107: 46272 | B107: Aros Rosella Plateados | C107: Único | D107: 1 | F107: =IF($B107="","",N($D107)*IF(N($E107)>0,$E107,IFERROR(INDEX(Costos!$I$23:$I$300,MATCH($B107,Costos!$A$23:$A$300,0)),0))) -> 7298.6403
A108: 46272 | B108: Aros Capri Vino | C108: Único | D108: 1 | F108: =IF($B108="","",N($D108)*IF(N($E108)>0,$E108,IFERROR(INDEX(Costos!$I$23:$I$300,MATCH($B108,Costos!$A$23:$A$300,0)),0))) -> 6373.6403
A109: 46272 | B109: Aros Capri Rosa | C109: Único | D109: 1 | F109: =IF($B109="","",N($D109)*IF(N($E109)>0,$E109,IFERROR(INDEX(Costos!$I$23:$I$300,MATCH($B109,Costos!$A$23:$A$300,0)),0))) -> 6373.6403
A110: 46272 | B110: Aros Capri Verde | C110: Único | D110: 1 | F110: =IF($B110="","",N($D110)*IF(N($E110)>0,$E110,IFERROR(INDEX(Costos!$I$23:$I$300,MATCH($B110,Costos!$A$23:$A$300,0)),0))) -> 8897.6403
A111: 46272 | B111: Aros Capri Blanco | C111: Único | D111: 1 | F111: =IF($B111="","",N($D111)*IF(N($E111)>0,$E111,IFERROR(INDEX(Costos!$I$23:$I$300,MATCH($B111,Costos!$A$23:$A$300,0)),0))) -> 8897.6403
A112: 46272 | B112: Anillo Corazón II Dorado | C112: Único | D112: 2 | F112: =IF($B112="","",N($D112)*IF(N($E112)>0,$E112,IFERROR(INDEX(Costos!$I$23:$I$300,MATCH($B112,Costos!$A$23:$A$300,0)),0))) -> 9401.2807
A113: 46272 | B113: Anillo Lia Dorado | C113: Único | D113: 2 | F113: =IF($B113="","",N($D113)*IF(N($E113)>0,$E113,IFERROR(INDEX(Costos!$I$23:$I$300,MATCH($B113,Costos!$A$23:$A$300,0)),0))) -> 9583.2807
A114: 46272 | B114: Anillo Lia Plateado | C114: Único | D114: 2 | F114: =IF($B114="","",N($D114)*IF(N($E114)>0,$E114,IFERROR(INDEX(Costos!$I$23:$I$300,MATCH($B114,Costos!$A$23:$A$300,0)),0))) -> 9583.2807
A115: 46272 | B115: Collar Amour Chunky | C115: Único | D115: 1 | F115: =IF($B115="","",N($D115)*IF(N($E115)>0,$E115,IFERROR(INDEX(Costos!$I$23:$I$300,MATCH($B115,Costos!$A$23:$A$300,0)),0))) -> 10658.64
A116: 46272 | B116: Aros Cuore | C116: Único | D116: 2 | F116: =IF($B116="","",N($D116)*IF(N($E116)>0,$E116,IFERROR(INDEX(Costos!$I$23:$I$300,MATCH($B116,Costos!$A$23:$A$300,0)),0))) -> 19791.281
... A120: 46272 | B120: Pulsera Bolitas | C120: Único | D120: 2 | F120: =IF($B120="","",N($D120)*IF(N($E120)>0,$E120,IFERROR(INDEX(Costos!$I$23:$I$300,MATCH($B120,Costos!$A$23:$A$300,0)),0))) -> 6689.2807
F121: =IF($B121="","",N($D121)*IF(N($E121)>0,$E121,IFERROR(INDEX(Costos!$I$23:$I$300,MATCH($B121,Costos!$A$23:$A$300,0)),0)))
F122: =IF($B122="","",N($D122)*IF(N($E122)>0,$E122,IFERROR(INDEX(Costos!$I$23:$I$300,MATCH($B122,Costos!$A$23:$A$300,0)),0)))
F123: =IF($B123="","",N($D123)*IF(N($E123)>0,$E123,IFERROR(INDEX(Costos!$I$23:$I$300,MATCH($B123,Costos!$A$23:$A$300,0)),0)))
...

Sheet Ventas
A1: VENTAS
A2: Una línea por cada venta. Elegí el producto de la lista y poné el talle solo si es anillo.
A3: Dejá el precio vacío para que tome tu precio de venta. Escribilo solo si hiciste un precio especial.
A5: Fecha | B5: Producto | C5: Talle | D5: Cantidad | E5: Precio unitario | F5: Total | G5: Clienta | H5: Notas
A6: 46243 | B6: Anillo calado | C6: Mediano | D6: 1 | F6: =IF($B6="","",N($D6)*IF(N($E6)>0,$E6,IFERROR(INDEX(Costos!$K$23:$K$300,MATCH($B6,Costos!$A$23:$A$300,0)),0))) -> 19000 | G6: gabi de simone
A7: 46243 | B7: Anillo calado | C7: Grande | D7: 1 | F7: =IF($B7="","",N($D7)*IF(N($E7)>0,$E7,IFERROR(INDEX(Costos!$K$23:$K$300,MATCH($B7,Costos!$A$23:$A$300,0)),0))) -> 19000 | G7: gabi de simone
A8: 46243 | B8: Cadena lisa | C8: Único | D8: 1 | F8: =IF($B8="","",N($D8)*IF(N($E8)>0,$E8,IFERROR(INDEX(Costos!$K$23:$K$300,MATCH($B8,Costos!$A$23:$A$300,0)),0))) -> 7000 | G8: gabi de simone
A9: 46251 | B9: Cubic Circulo Docha | C9: Único | D9: 1 | F9: =IF($B9="","",N($D9)*IF(N($E9)>0,$E9,IFERROR(INDEX(Costos!$K$23:$K$300,MATCH($B9,Costos!$A$23:$A$300,0)),0))) -> 12500 | G9: abueka
A10: 46251 | B10: Argollitas Classic N°1 | C10: Único | D10: 1 | F10: =IF($B10="","",N($D10)*IF(N($E10)>0,$E10,IFERROR(INDEX(Costos!$K$23:$K$300,MATCH($B10,Costos!$A$23:$A$300,0)),0))) -> 7000 | G10: valen
A11: 46251 | B11: Argollitas Classic N°2 | C11: Único | D11: 1 | F11: =IF($B11="","",N($D11)*IF(N($E11)>0,$E11,IFERROR(INDEX(Costos!$K$23:$K$300,MATCH($B11,Costos!$A$23:$A$300,0)),0))) -> 7500 | G11: valen
A12: 46251 | B12: Argollitas gota | C12: Único | D12: 1 | F12: =IF($B12="","",N($D12)*IF(N($E12)>0,$E12,IFERROR(INDEX(Costos!$K$23:$K$300,MATCH($B12,Costos!$A$23:$A$300,0)),0))) -> 7500 | G12: valen
A13: 46252 | B13: Anillo Ovalo | C13: Único | D13: 1 | F13: =IF($B13="","",N($D13)*IF(N($E13)>0,$E13,IFERROR(INDEX(Costos!$K$23:$K$300,MATCH($B13,Costos!$A$23:$A$300,0)),0))) -> 11500 | G13: valen
A14: 46252 | B14: Anillo Irregular | C14: Único | D14: 1 | F14: =IF($B14="","",N($D14)*IF(N($E14)>0,$E14,IFERROR(INDEX(Costos!$K$23:$K$300,MATCH($B14,Costos!$A$23:$A$300,0)),0))) -> 11500 | G14: valen
A15: 46254 | B15: Anillo Vanton | C15: Único | D15: 1 | F15: =IF($B15="","",N($D15)*IF(N($E15)>0,$E15,IFERROR(INDEX(Costos!$K$23:$K$300,MATCH($B15,Costos!$A$23:$A$300,0)),0))) -> 11500 | G15: caro
A16: 46254 | B16: Anillo Zafira | C16: Único | D16: 1 | F16: =IF($B16="","",N($D16)*IF(N($E16)>0,$E16,IFERROR(INDEX(Costos!$K$23:$K$300,MATCH($B16,Costos!$A$23:$A$300,0)),0))) -> 13000 | G16: caro
A17: 46254 | B17: Anillo Sin Fin | C17: Mediano | D17: 1 | F17: =IF($B17="","",N($D17)*IF(N($E17)>0,$E17,IFERROR(INDEX(Costos!$K$23:$K$300,MATCH($B17,Costos!$A$23:$A$300,0)),0))) -> 20000 | G17: vicky
A18: 46254 | B18: Anillo Vanton | C18: Único | D18: 1 | E18: 0 | F18: =IF($B18="","",N($D18)*IF(N($E18)>0,$E18,IFERROR(INDEX(Costos!$K$23:$K$300,MATCH($B18,Costos!$A$23:$A$300,0)),0))) -> 11500 | G18: LO PERDI
A19: 46254 | B19: Anillo Nodo | C19: Único | D19: 1 | F19: =IF($B19="","",N($D19)*IF(N($E19)>0,$E19,IFERROR(INDEX(Costos!$K$23:$K$300,MATCH($B19,Costos!$A$23:$A$300,0)),0))) -> 13000 | G19: abuela para regalo gabi
A20: 46254 | B20: Anillo Virel | C20: Único | D20: 1 | F20: =IF($B20="","",N($D20)*IF(N($E20)>0,$E20,IFERROR(INDEX(Costos!$K$23:$K$300,MATCH($B20,Costos!$A$23:$A$300,0)),0))) -> 12000 | G20: abuela para regalo gabi
A21: 46256 | B21: Cubic Mini Circulo | C21: Único | D21: 1 | F21: =IF($B21="","",N($D21)*IF(N($E21)>0,$E21,IFERROR(INDEX(Costos!$K$23:$K$300,MATCH($B21,Costos!$A$23:$A$300,0)),0))) -> 12000 | G21: mica
A22: 46256 | B22: Anillo Azmira | C22: Único | D22: 1 | F22: =IF($B22="","",N($D22)*IF(N($E22)>0,$E22,IFERROR(INDEX(Costos!$K$23:$K$300,MATCH($B22,Costos!$A$23:$A$300,0)),0))) -> 11500 | G22: abuela piqui
A23: 46256 | B23: Anillo Gota | C23: Mediano | D23: 1 | F23: =IF($B23="","",N($D23)*IF(N($E23)>0,$E23,IFERROR(INDEX(Costos!$K$23:$K$300,MATCH($B23,Costos!$A$23:$A$300,0)),0))) -> 23000 | G23: abuela piqui
A24: 46256 | B24: Anillo Mina | C24: Único | D24: 1 | F24: =IF($B24="","",N($D24)*IF(N($E24)>0,$E24,IFERROR(INDEX(Costos!$K$23:$K$300,MATCH($B24,Costos!$A$23:$A$300,0)),0))) -> 13000 | G24: tia nariana
A25: 46256 | B25: Anillo Virel | C25: Único | D25: 1 | F25: =IF($B25="","",N($D25)*IF(N($E25)>0,$E25,IFERROR(INDEX(Costos!$K$23:$K$300,MATCH($B25,Costos!$A$23:$A$300,0)),0))) -> 12000 | G25: tia nariana
A26: 46256 | B26: Anillo Mina | C26: Único | D26: 1 | E26: 0 | F26: =IF($B26="","",N($D26)*IF(N($E26)>0,$E26,IFERROR(INDEX(Costos!$K$23:$K$300,MATCH($B26,Costos!$A$23:$A$300,0)),0))) -> 13000 | G26: VALEN | H26: SE ROMPIO
A27: 46258 | B27: Anillo Circulo | C27: Chico | D27: 1 | F27: =IF($B27="","",N($D27)*IF(N($E27)>0,$E27,IFERROR(INDEX(Costos!$K$23:$K$300,MATCH($B27,Costos!$A$23:$A$300,0)),0))) -> 16000 | G27: gabi de simone | H27: PARA LA HERMANA
A28: 46258 | B28: Argollitas Classic N°3 | C28: Único | D28: 1 | F28: =IF($B28="","",N($D28)*IF(N($E28)>0,$E28,IFERROR(INDEX(Costos!$K$23:$K$300,MATCH($B28,Costos!$A$23:$A$300,0)),0))) -> 8000 | G28: gabi de simone | H28: PARA LA HERMANA
A29: 46258 | B29: Argollitas Classic N°4 | C29: Único | D29: 1 | E29: 0 | F29: =IF($B29="","",N($D29)*IF(N($E29)>0,$E29,IFERROR(INDEX(Costos!$K$23:$K$300,MATCH($B29,Costos!$A$23:$A$300,0)),0))) -> 8500 | G29: está fallado | H29: SE ROMPIO
A30: 46260 | B30: Argollitas 10mm | C30: Único | D30: 1 | E30: 0 | F30: =IF($B30="","",N($D30)*IF(N($E30)>0,$E30,IFERROR(INDEX(Costos!$K$23:$K$300,MATCH($B30,Costos!$A$23:$A$300,0)),0))) -> 7000 | G30: se me rompio | H30: SE ROMPIO
A31: 46260 | B31: Cubic Mini cuadrado | C31: Único | D31: 1 | F31: =IF($B31="","",N($D31)*IF(N($E31)>0,$E31,IFERROR(INDEX(Costos!$K$23:$K$300,MATCH($B31,Costos!$A$23:$A$300,0)),0))) -> 12000 | G31: lola gogo
A32: 46260 | B32: Anillo Vena | C32: Único | D32: 1 | F32: =IF($B32="","",N($D32)*IF(N($E32)>0,$E32,IFERROR(INDEX(Costos!$K$23:$K$300,MATCH($B32,Costos!$A$23:$A$300,0)),0))) -> 25000 | G32: lola gogo
A33: 46260 | B33: Collar Muna Circulo | C33: Único | D33: 1 | F33: =IF($B33="","",N($D33)*IF(N($E33)>0,$E33,IFERROR(INDEX(Costos!$K$23:$K$300,MATCH($B33,Costos!$A$23:$A$300,0)),0))) -> 30000 | G33: gabriela juliano (mama
A34: 46260 | B34: Collar Fino Circulo | C34: Único | D34: 1 | F34: =IF($B34="","",N($D34)*IF(N($E34)>0,$E34,IFERROR(INDEX(Costos!$K$23:$K$300,MATCH($B34,Costos!$A$23:$A$300,0)),0))) -> 28000 | G34: abuela
A35: 46261 | B35: Anillos Corazones III | C35: Único | D35: 1 | F35: =IF($B35="","",N($D35)*IF(N($E35)>0,$E35,IFERROR(INDEX(Costos!$K$23:$K$300,MATCH($B35,Costos!$A$23:$A$300,0)),0))) -> 23500 | G35: vicky
A36: 46261 | B36: Collar Muna Corazón | C36: Único | D36: 1 | F36: =IF($B36="","",N($D36)*IF(N($E36)>0,$E36,IFERROR(INDEX(Costos!$K$23:$K$300,MATCH($B36,Costos!$A$23:$A$300,0)),0))) -> 31000 | G36: nico leandro grinfield
A37: 46261 | B37: Argollitas Caviar circulo | C37: Único | D37: 1 | F37: =IF($B37="","",N($D37)*IF(N($E37)>0,$E37,IFERROR(INDEX(Costos!$K$23:$K$300,MATCH($B37,Costos!$A$23:$A$300,0)),0))) -> 6500 | G37: nico leandro grinfield
A38: 46261 | B38: Anillo Sin Fin | C38: Mediano | D38: 1 | F38: =IF($B38="","",N($D38)*IF(N($E38)>0,$E38,IFERROR(INDEX(Costos!$K$23:$K$300,MATCH($B38,Costos!$A$23:$A$300,0)),0))) -> 20000 | G38: gaby de simone
A39: 46261 | B39: Anillo Irregular | C39: Único | D39: 1 | F39: =IF($B39="","",N($D39)*IF(N($E39)>0,$E39,IFERROR(INDEX(Costos!$K$23:$K$300,MATCH($B39,Costos!$A$23:$A$300,0)),0))) -> 11500 | G39: gaby de simone
A40: 46261 | B40: Cubic Mini cuadrado | C40: Único | D40: 1 | F40: =IF($B40="","",N($D40)*IF(N($E40)>0,$E40,IFERROR(INDEX(Costos!$K$23:$K$300,MATCH($B40,Costos!$A$23:$A$300,0)),0))) -> 12000 | G40: juli mama
A41: 46261 | B41: Anillo Sin Fin | C41: Mediano | D41: 1 | F41: =IF($B41="","",N($D41)*IF(N($E41)>0,$E41,IFERROR(INDEX(Costos!$K$23:$K$300,MATCH($B41,Costos!$A$23:$A$300,0)),0))) -> 20000 | G41: juli mama
A42: 46261 | B42: Anillo Vera | C42: Grande | D42: 1 | F42: =IF($B42="","",N($D42)*IF(N($E42)>0,$E42,IFERROR(INDEX(Costos!$K$23:$K$300,MATCH($B42,Costos!$A$23:$A$300,0)),0))) -> 22500 | G42: juli mama
... A50: 46261 | B50: Cadena lisa | C50: Único | D50: 1 | F50: =IF($B50="","",N($D50)*IF(N($E50)>0,$E50,IFERROR(INDEX(Costos!$K$23:$K$300,MATCH($B50,Costos!$A$23:$A$300,0)),0))) -> 7000 | G50: valen a costo
A51: 46261 | B51: Cubic Cuadrado | C51: Único | D51: 1 | F51: =IF($B51="","",N($D51)*IF(N($E51)>0,$E51,IFERROR(INDEX(Costos!$K$23:$K$300,MATCH($B51,Costos!$A$23:$A$300,0)),0))) -> 12500 | H51: SE ROMPIO
A52: 46263 | B52: Argollitas Ocampo | C52: Único | D52: 1 | F52: =IF($B52="","",N($D52)*IF(N($E52)>0,$E52,IFERROR(INDEX(Costos!$K$23:$K$300,MATCH($B52,Costos!$A$23:$A$300,0)),0))) -> 7000 | G52: daniela la porta amiga mama
A53: 46263 | B53: Anillo Corazón II Plateado | C53: Único | D53: 1 | F53: =IF($B53="","",N($D53)*IF(N($E53)>0,$E53,IFERROR(INDEX(Costos!$K$23:$K$300,MATCH($B53,Costos!$A$23:$A$300,0)),0))) -> 12000 | G53: lore sanleone
A54: 46263 | B54: Anillo Deriva | C54: Único | D54: 1 | F54: =IF($B54="","",N($D54)*IF(N($E54)>0,$E54,IFERROR(INDEX(Costos!$K$23:$K$300,MATCH($B54,Costos!$A$23:$A$300,0)),0))) -> 25500 | G54: lore sanleone
A55: 46263 | B55: Argollitas Marco Docha | C55: Único | D55: 1 | F55: =IF($B55="","",N($D55)*IF(N($E55)>0,$E55,IFERROR(INDEX(Costos!$K$23:$K$300,MATCH($B55,Costos!$A$23:$A$300,0)),0))) -> 25000 | G55: lore sanleone
A56: 46263 | B56: Aros Halo N°2 (14 mm) | C56: Único | D56: 1 | F56: =IF($B56="","",N($D56)*IF(N($E56)>0,$E56,IFERROR(INDEX(Costos!$K$23:$K$300,MATCH($B56,Costos!$A$23:$A$300,0)),0))) -> 25000 | G56: mariela
A57: 46266 | B57: Anillo Star | C57: Único | D57: 1 | F57: =IF($B57="","",N($D57)*IF(N($E57)>0,$E57,IFERROR(INDEX(Costos!$K$23:$K$300,MATCH($B57,Costos!$A$23:$A$300,0)),0))) -> 11500 | G57: zoe alumna
A58: 46267 | B58: Anillo Circulo | C58: Mediano | D58: 1 | F58: =IF($B58="","",N($D58)*IF(N($E58)>0,$E58,IFERROR(INDEX(Costos!$K$23:$K$300,MATCH($B58,Costos!$A$23:$A$300,0)),0))) -> 16000 | G58: caro
A59: 46267 | B59: Collar Amour | C59: Único | D59: 1 | F59: =IF($B59="","",N($D59)*IF(N($E59)>0,$E59,IFERROR(INDEX(Costos!$K$23:$K$300,MATCH($B59,Costos!$A$23:$A$300,0)),0))) -> 15000 | G59: lau mama schuster
A60: 46267 | B60: Aros Atlas | C60: Único | D60: 1 | F60: =IF($B60="","",N($D60)*IF(N($E60)>0,$E60,IFERROR(INDEX(Costos!$K$23:$K$300,MATCH($B60,Costos!$A$23:$A$300,0)),0))) -> 16500 | G60: lau mama schuster
A61: 46267 | B61: Argollitas Classic N°1 D | C61: Único | D61: 1 | F61: =IF($B61="","",N($D61)*IF(N($E61)>0,$E61,IFERROR(INDEX(Costos!$K$23:$K$300,MATCH($B61,Costos!$A$23:$A$300,0)),0))) -> 9000 | G61: mama
A62: 46267 | B62: Aros Nara | C62: Único | D62: 1 | F62: =IF($B62="","",N($D62)*IF(N($E62)>0,$E62,IFERROR(INDEX(Costos!$K$23:$K$300,MATCH($B62,Costos!$A$23:$A$300,0)),0))) -> 15000 | G62: gabi fortunato
A63: 46267 | B63: Aros Rosella Dorado | C63: Único | D63: 1 | F63: =IF($B63="","",N($D63)*IF(N($E63)>0,$E63,IFERROR(INDEX(Costos!$K$23:$K$300,MATCH($B63,Costos!$A$23:$A$300,0)),0))) -> 15000 | G63: marisa mikluch
... A67: 46274 | B67: Argollitas Classic N°5 | C67: Único | D67: 1 | F67: =IF($B67="","",N($D67)*IF(N($E67)>0,$E67,IFERROR(INDEX(Costos!$K$23:$K$300,MATCH($B67,Costos!$A$23:$A$300,0)),0))) -> 9000 | G67: juana torras random
A68: 46276 | B68: Anillo Sin Fin | C68: Mediano | D68: 1 | F68: =IF($B68="","",N($D68)*IF(N($E68)>0,$E68,IFERROR(INDEX(Costos!$K$23:$K$300,MATCH($B68,Costos!$A$23:$A$300,0)),0))) -> 20000 | G68: mia heredia | H68: FALTA PAGAR
A69: 46276 | B69: Anillo Sin Fin | C69: Mediano | D69: 1 | F69: =IF($B69="","",N($D69)*IF(N($E69)>0,$E69,IFERROR(INDEX(Costos!$K$23:$K$300,MATCH($B69,Costos!$A$23:$A$300,0)),0))) -> 20000 | G69: loli
A70: 46276 | B70: Collar Amour | C70: Único | D70: 1 | F70: =IF($B70="","",N($D70)*IF(N($E70)>0,$E70,IFERROR(INDEX(Costos!$K$23:$K$300,MATCH($B70,Costos!$A$23:$A$300,0)),0))) -> 15000 | G70: kari zoe
A71: 46276 | B71: Argollitas Caviar triangulo | C71: Único | D71: 1 | F71: =IF($B71="","",N($D71)*IF(N($E71)>0,$E71,IFERROR(INDEX(Costos!$K$23:$K$300,MATCH($B71,Costos!$A$23:$A$300,0)),0))) -> 6500 | G71: kari zoe
A72: 46276 | B72: Argollita Duna N°0 | C72: Único | D72: 1 | F72: =IF($B72="","",N($D72)*IF(N($E72)>0,$E72,IFERROR(INDEX(Costos!$K$23:$K$300,MATCH($B72,Costos!$A$23:$A$300,0)),0))) -> 6500 | G72: kari zoe
F73: =IF($B73="","",N($D73)*IF(N($E73)>0,$E73,IFERROR(INDEX(Costos!$K$23:$K$300,MATCH($B73,Costos!$A$23:$A$300,0)),0))) | G73: kari zoe
B74: pu | C74: Único | F74: =IF($B74="","",N($D74)*IF(N($E74)>0,$E74,IFERROR(INDEX(Costos!$K$23:$K$300,MATCH($B74,Costos!$A$23:$A$300,0)),0))) -> 0 | G74: kari zoe
F75: =IF($B75="","",N($D75)*IF(N($E75)>0,$E75,IFERROR(INDEX(Costos!$K$23:$K$300,MATCH($B75,Costos!$A$23:$A$300,0)),0)))
F76: =IF($B76="","",N($D76)*IF(N($E76)>0,$E76,IFERROR(INDEX(Costos!$K$23:$K$300,MATCH($B76,Costos!$A$23:$A$300,0)),0)))
F77: =IF($B77="","",N($D77)*IF(N($E77)>0,$E77,IFERROR(INDEX(Costos!$K$23:$K$300,MATCH($B77,Costos!$A$23:$A$300,0)),0)))
F78: =IF($B78="","",N($D78)*IF(N($E78)>0,$E78,IFERROR(INDEX(Costos!$K$23:$K$300,MATCH($B78,Costos!$A$23:$A$300,0)),0)))
F79: =IF($B79="","",N($D79)*IF(N($E79)>0,$E79,IFERROR(INDEX(Costos!$K$23:$K$300,MATCH($B79,Costos!$A$23:$A$300,0)),0)))
F80: =IF($B80="","",N($D80)*IF(N($E80)>0,$E80,IFERROR(INDEX(Costos!$K$23:$K$300,MATCH($B80,Costos!$A$23:$A$300,0)),0)))
F81: =IF($B81="","",N($D81)*IF(N($E81)>0,$E81,IFERROR(INDEX(Costos!$K$23:$K$300,MATCH($B81,Costos!$A$23:$A$300,0)),0)))
F82: =IF($B82="","",N($D82)*IF(N($E82)>0,$E82,IFERROR(INDEX(Costos!$K$23:$K$300,MATCH($B82,Costos!$A$23:$A$300,0)),0)))
F83: =IF($B83="","",N($D83)*IF(N($E83)>0,$E83,IFERROR(INDEX(Costos!$K$23:$K$300,MATCH($B83,Costos!$A$23:$A$300,0)),0)))
F84: =IF($B84="","",N($D84)*IF(N($E84)>0,$E84,IFERROR(INDEX(Costos!$K$23:$K$300,MATCH($B84,Costos!$A$23:$A$300,0)),0)))
F85: =IF($B85="","",N($D85)*IF(N($E85)>0,$E85,IFERROR(INDEX(Costos!$K$23:$K$300,MATCH($B85,Costos!$A$23:$A$300,0)),0)))
F86: =IF($B86="","",N($D86)*IF(N($E86)>0,$E86,IFERROR(INDEX(Costos!$K$23:$K$300,MATCH($B86,Costos!$A$23:$A$300,0)),0)))
... F605: =IF($B605="","",N($D605)*IF(N($E605)>0,$E605,IFERROR(INDEX(Costos!$K$23:$K$300,MATCH($B605,Costos!$A$23:$A$300,0)),0)))
A608: Si dejás el precio vacío se usa el Precio de venta de la hoja Costos.

Sheet Stock
A1: STOCK
A2: Esta hoja se calcula sola desde Compras y Ventas. Acá no cargues nada.
A3: Para descontar una venta, agregá la línea en la hoja Ventas.
A5: Avisame cuando queden | B5: 1 | C5: o menos | E5: Piezas en stock | F5: =SUM(H9:H108) -> 69 | H5: Invertido: | I5: =SUM(Compras!F:F) -> 1321362.3 | J5: Facturado: | K5: =SUM(Ventas!$F$6:$F$605) -> 978500 | L5: Ganancia: | M5: {=SUM(Ventas!F:F)-SUMPRODUCT(Ventas!D6:D1000,IFERROR(VLOOKUP(Ventas!B6:B1000,Costos!A:I,9,FALSE()),0))} -> 412618.9 | N5: pasa eso porque todavia no vendi todo lo que esta en stock
A8: Producto | B8: Material | C8: Categoría | D8: Único | E8: Chico | F8: Mediano | G8: Grande | H8: Total | I8: Estado | J8: Vendidas | K8: Facturado
A9: =IF(Costos!$A23="","",Costos!$A23) -> Argollitas Classic N°1 | B9: =IF(Costos!$A23="","",Costos!$B23&"") -> Plata 925 | C9: =IF(Costos!$A23="","",Costos!$C23&"") -> Aros | D9: =IF($A9="","",SUMIFS(Compras!$D$6:$D$605,Compras!$B$6:$B$605,$A9,Compras!$C$6:$C$605,"Único")-SUMIFS(Ventas!$D$6:$D$605,Ventas!$B$6:$B$605,$A9,Ventas!$C$6:$C$605,"Único")) -> 0 | E9: =IF($A9="","",IF(LEFT($C9,6)="Anillo",SUMIFS(Compras!$D$6:$D$605,Compras!$B$6:$B$605,$A9,Compras!$C$6:$C$605,"Chico")-SUMIFS(Ventas!$D$6:$D$605,Ventas!$B$6:$B$605,$A9,Ventas!$C$6:$C$605,"Chico"),"")) | F9: =IF($A9="","",IF(LEFT($C9,6)="Anillo",SUMIFS(Compras!$D$6:$D$605,Compras!$B$6:$B$605,$A9,Compras!$C$6:$C$605,"Mediano")-SUMIFS(Ventas!$D$6:$D$605,Ventas!$B$6:$B$605,$A9,Ventas!$C$6:$C$605,"Mediano"),"")) | G9: =IF($A9="","",IF(LEFT($C9,6)="Anillo",SUMIFS(Compras!$D$6:$D$605,Compras!$B$6:$B$605,$A9,Compras!$C$6:$C$605,"Grande")-SUMIFS(Ventas!$D$6:$D$605,Ventas!$B$6:$B$605,$A9,Ventas!$C$6:$C$605,"Grande"),"")) | H9: =IF($A9="","",N($D9)+N($E9)+N($F9)+N($G9)) -> 0 | I9: =IF($A9="","",IF(N($H9)<=0,"SIN STOCK",IF(LEFT($C9,6)="Anillo",IF(IF(AND(SUMIFS(Compras!$D$6:$D$605,Compras!$B$6:$B$605,$A9,Compras!$C$6:$C$605,"Chico")>0,N($E9)<=$B$5),"C ","")&IF(AND(SUMIFS(Compras!$D$6:$D$605,Compras!$B$6:$B$605,$A9,Compras!$C$6:$C$605,"Mediano")>0,N($F9)<=$B$5),"M ","")&IF(AND(SUMIFS(Compras!$D$6:$D$605,Compras!$B$6:$B$605,$A9,Compras!$C$6:$C$605,"Grande")>0,N($G9)<=$B$5),"G","")="","","Reponer "&IF(AND(SUMIFS(Compras!$D$6:$D$605,Compras!$B$6:$B$605,$A9,Compras!$C$6:$C$605,"Chico")>0,N($E9)<=$B$5),"C ","")&IF(AND(SUMIFS(Compras!$D$6:$D$605,Compras!$B$6:$B$605,$A9,Compras!$C$6:$C$605,"Mediano")>0,N($F9)<=$B$5),"M ","")&IF(AND(SUMIFS(Compras!$D$6:$D$605,Compras!$B$6:$B$605,$A9,Compras!$C$6:$C$605,"Grande")>0,N($G9)<=$B$5),"G","")),IF(N($H9)<=$B$5,"REPONER","")))) -> SIN STOCK | J9: =IF($A9="","",SUMIFS(Ventas!$D$6:$D$605,Ventas!$B$6:$B$605,$A9)) -> 1 | K9: =IF($A9="","",SUMIFS(Ventas!$F$6:$F$605,Ventas!$B$6:$B$605,$A9)) -> 7000
A10: =IF(Costos!$A24="","",Costos!$A24) -> Argollitas Classic N°2 | B10: =IF(Costos!$A24="","",Costos!$B24&"") -> Plata 925 | C10: =IF(Costos!$A24="","",Costos!$C24&"") -> Aros | D10: =IF($A10="","",SUMIFS(Compras!$D$6:$D$605,Compras!$B$6:$B$605,$A10,Compras!$C$6:$C$605,"Único")-SUMIFS(Ventas!$D$6:$D$605,Ventas!$B$6:$B$605,$A10,Ventas!$C$6:$C$605,"Único")) -> 0 | E10: =IF($A10="","",IF(LEFT($C10,6)="Anillo",SUMIFS(Compras!$D$6:$D$605,Compras!$B$6:$B$605,$A10,Compras!$C$6:$C$605,"Chico")-SUMIFS(Ventas!$D$6:$D$605,Ventas!$B$6:$B$605,$A10,Ventas!$C$6:$C$605,"Chico"),"")) | F10: =IF($A10="","",IF(LEFT($C10,6)="Anillo",SUMIFS(Compras!$D$6:$D$605,Compras!$B$6:$B$605,$A10,Compras!$C$6:$C$605,"Mediano")-SUMIFS(Ventas!$D$6:$D$605,Ventas!$B$6:$B$605,$A10,Ventas!$C$6:$C$605,"Mediano"),"")) | G10: =IF($A10="","",IF(LEFT($C10,6)="Anillo",SUMIFS(Compras!$D$6:$D$605,Compras!$B$6:$B$605,$A10,Compras!$C$6:$C$605,"Grande")-SUMIFS(Ventas!$D$6:$D$605,Ventas!$B$6:$B$605,$A10,Ventas!$C$6:$C$605,"Grande"),"")) | H10: =IF($A10="","",N($D10)+N($E10)+N($F10)+N($G10)) -> 0 | I10: =IF($A10="","",IF(N($H10)<=0,"SIN STOCK",IF(LEFT($C10,6)="Anillo",IF(IF(AND(SUMIFS(Compras!$D$6:$D$605,Compras!$B$6:$B$605,$A10,Compras!$C$6:$C$605,"Chico")>0,N($E10)<=$B$5),"C ","")&IF(AND(SUMIFS(Compras!$D$6:$D$605,Compras!$B$6:$B$605,$A10,Compras!$C$6:$C$605,"Mediano")>0,N($F10)<=$B$5),"M ","")&IF(AND(SUMIFS(Compras!$D$6:$D$605,Compras!$B$6:$B$605,$A10,Compras!$C$6:$C$605,"Grande")>0,N($G10)<=$B$5),"G","")="","","Reponer "&IF(AND(SUMIFS(Compras!$D$6:$D$605,Compras!$B$6:$B$605,$A10,Compras!$C$6:$C$605,"Chico")>0,N($E10)<=$B$5),"C ","")&IF(AND(SUMIFS(Compras!$D$6:$D$605,Compras!$B$6:$B$605,$A10,Compras!$C$6:$C$605,"Mediano")>0,N($F10)<=$B$5),"M ","")&IF(AND(SUMIFS(Compras!$D$6:$D$605,Compras!$B$6:$B$605,$A10,Compras!$C$6:$C$605,"Grande")>0,N($G10)<=$B$5),"G","")),IF(N($H10)<=$B$5,"REPONER","")))) -> SIN STOCK | J10: =IF($A10="","",SUMIFS(Ventas!$D$6:$D$605,Ventas!$B$6:$B$605,$A10)) -> 1 | K10: =IF($A10="","",SUMIFS(Ventas!$F$6:$F$605,Ventas!$B$6:$B$605,$A10)) -> 7500
A11: =IF(Costos!$A25="","",Costos!$A25) -> Argollitas Classic N°3 | B11: =IF(Costos!$A25="","",Costos!$B25&"") -> Plata 925 | C11: =IF(Costos!$A25="","",Costos!$C25&"") -> Aros | D11: =IF($A11="","",SUMIFS(Compras!$D$6:$D$605,Compras!$B$6:$B$605,$A11,Compras!$C$6:$C$605,"Único")-SUMIFS(Ventas!$D$6:$D$605,Ventas!$B$6:$B$605,$A11,Ventas!$C$6:$C$605,"Único")) -> 0 | E11: =IF($A11="","",IF(LEFT($C11,6)="Anillo",SUMIFS(Compras!$D$6:$D$605,Compras!$B$6:$B$605,$A11,Compras!$C$6:$C$605,"Chico")-SUMIFS(Ventas!$D$6:$D$605,Ventas!$B$6:$B$605,$A11,Ventas!$C$6:$C$605,"Chico"),"")) | F11: =IF($A11="","",IF(LEFT($C11,6)="Anillo",SUMIFS(Compras!$D$6:$D$605,Compras!$B$6:$B$605,$A11,Compras!$C$6:$C$605,"Mediano")-SUMIFS(Ventas!$D$6:$D$605,Ventas!$B$6:$B$605,$A11,Ventas!$C$6:$C$605,"Mediano"),"")) | G11: =IF($A11="","",IF(LEFT($C11,6)="Anillo",SUMIFS(Compras!$D$6:$D$605,Compras!$B$6:$B$605,$A11,Compras!$C$6:$C$605,"Grande")-SUMIFS(Ventas!$D$6:$D$605,Ventas!$B$6:$B$605,$A11,Ventas!$C$6:$C$605,"Grande"),"")) | H11: =IF($A11="","",N($D11)+N($E11)+N($F11)+N($G11)) -> 0 | I11: =IF($A11="","",IF(N($H11)<=0,"SIN STOCK",IF(LEFT($C11,6)="Anillo",IF(IF(AND(SUMIFS(Compras!$D$6:$D$605,Compras!$B$6:$B$605,$A11,Compras!$C$6:$C$605,"Chico")>0,N($E11)<=$B$5),"C ","")&IF(AND(SUMIFS(Compras!$D$6:$D$605,Compras!$B$6:$B$605,$A11,Compras!$C$6:$C$605,"Mediano")>0,N($F11)<=$B$5),"M ","")&IF(AND(SUMIFS(Compras!$D$6:$D$605,Compras!$B$6:$B$605,$A11,Compras!$C$6:$C$605,"Grande")>0,N($G11)<=$B$5),"G","")="","","Reponer "&IF(AND(SUMIFS(Compras!$D$6:$D$605,Compras!$B$6:$B$605,$A11,Compras!$C$6:$C$605,"Chico")>0,N($E11)<=$B$5),"C ","")&IF(AND(SUMIFS(Compras!$D$6:$D$605,Compras!$B$6:$B$605,$A11,Compras!$C$6:$C$605,"Mediano")>0,N($F11)<=$B$5),"M ","")&IF(AND(SUMIFS(Compras!$D$6:$D$605,Compras!$B$6:$B$605,$A11,Compras!$C$6:$C$605,"Grande")>0,N($G11)<=$B$5),"G","")),IF(N($H11)<=$B$5,"REPONER","")))) -> SIN STOCK | J11: =IF($A11="","",SUMIFS(Ventas!$D$6:$D$605,Ventas!$B$6:$B$605,$A11)) -> 1 | K11: =IF($A11="","",SUMIFS(Ventas!$F$6:$F$605,Ventas!$B$6:$B$605,$A11)) -> 8000
A12: =IF(Costos!$A26="","",Costos!$A26) -> Argollitas Classic N°4 | B12: =IF(Costos!$A26="","",Costos!$B26&"") -> Plata 925 | C12: =IF(Costos!$A26="","",Costos!$C26&"") -> Aros | D12: =IF($A12="","",SUMIFS(Compras!$D$6:$D$605,Compras!$B$6:$B$605,$A12,Compras!$C$6:$C$605,"Único")-SUMIFS(Ventas!$D$6:$D$605,Ventas!$B$6:$B$605,$A12,Ventas!$C$6:$C$605,"Único")) -> 0 | E12: =IF($A12="","",IF(LEFT($C12,6)="Anillo",SUMIFS(Compras!$D$6:$D$605,Compras!$B$6:$B$605,$A12,Compras!$C$6:$C$605,"Chico")-SUMIFS(Ventas!$D$6:$D$605,Ventas!$B$6:$B$605,$A12,Ventas!$C$6:$C$605,"Chico"),"")) | F12: =IF($A12="","",IF(LEFT($C12,6)="Anillo",SUMIFS(Compras!$D$6:$D$605,Compras!$B$6:$B$605,$A12,Compras!$C$6:$C$605,"Mediano")-SUMIFS(Ventas!$D$6:$D$605,Ventas!$B$6:$B$605,$A12,Ventas!$C$6:$C$605,"Mediano"),"")) | G12: =IF($A12="","",IF(LEFT($C12,6)="Anillo",SUMIFS(Compras!$D$6:$D$605,Compras!$B$6:$B$605,$A12,Compras!$C$6:$C$605,"Grande")-SUMIFS(Ventas!$D$6:$D$605,Ventas!$B$6:$B$605,$A12,Ventas!$C$6:$C$605,"Grande"),"")) | H12: =IF($A12="","",N($D12)+N($E12)+N($F12)+N($G12)) -> 0 | I12: =IF($A12="","",IF(N($H12)<=0,"SIN STOCK",IF(LEFT($C12,6)="Anillo",IF(IF(AND(SUMIFS(Compras!$D$6:$D$605,Compras!$B$6:$B$605,$A12,Compras!$C$6:$C$605,"Chico")>0,N($E12)<=$B$5),"C ","")&IF(AND(SUMIFS(Compras!$D$6:$D$605,Compras!$B$6:$B$605,$A12,Compras!$C$6:$C$605,"Mediano")>0,N($F12)<=$B$5),"M ","")&IF(AND(SUMIFS(Compras!$D$6:$D$605,Compras!$B$6:$B$605,$A12,Compras!$C$6:$C$605,"Grande")>0,N($G12)<=$B$5),"G","")="","","Reponer "&IF(AND(SUMIFS(Compras!$D$6:$D$605,Compras!$B$6:$B$605,$A12,Compras!$C$6:$C$605,"Chico")>0,N($E12)<=$B$5),"C ","")&IF(AND(SUMIFS(Compras!$D$6:$D$605,Compras!$B$6:$B$605,$A12,Compras!$C$6:$C$605,"Mediano")>0,N($F12)<=$B$5),"M ","")&IF(AND(SUMIFS(Compras!$D$6:$D$605,Compras!$B$6:$B$605,$A12,Compras!$C$6:$C$605,"Grande")>0,N($G12)<=$B$5),"G","")),IF(N($H12)<=$B$5,"REPONER","")))) -> SIN STOCK | J12: =IF($A12="","",SUMIFS(Ventas!$D$6:$D$605,Ventas!$B$6:$B$605,$A12)) -> 1 | K12: =IF($A12="","",SUMIFS(Ventas!$F$6:$F$605,Ventas!$B$6:$B$605,$A12)) -> 8500
A13: =IF(Costos!$A27="","",Costos!$A27) -> Argollitas Classic N°5 | B13: =IF(Costos!$A27="","",Costos!$B27&"") -> Plata 925 | C13: =IF(Costos!$A27="","",Costos!$C27&"") -> Aros | D13: =IF($A13="","",SUMIFS(Compras!$D$6:$D$605,Compras!$B$6:$B$605,$A13,Compras!$C$6:$C$605,"Único")-SUMIFS(Ventas!$D$6:$D$605,Ventas!$B$6:$B$605,$A13,Ventas!$C$6:$C$605,"Único")) -> 1 | E13: =IF($A13="","",IF(LEFT($C13,6)="Anillo",SUMIFS(Compras!$D$6:$D$605,Compras!$B$6:$B$605,$A13,Compras!$C$6:$C$605,"Chico")-SUMIFS(Ventas!$D$6:$D$605,Ventas!$B$6:$B$605,$A13,Ventas!$C$6:$C$605,"Chico"),"")) | F13: =IF($A13="","",IF(LEFT($C13,6)="Anillo",SUMIFS(Compras!$D$6:$D$605,Compras!$B$6:$B$605,$A13,Compras!$C$6:$C$605,"Mediano")-SUMIFS(Ventas!$D$6:$D$605,Ventas!$B$6:$B$605,$A13,Ventas!$C$6:$C$605,"Mediano"),"")) | G13: =IF($A13="","",IF(LEFT($C13,6)="Anillo",SUMIFS(Compras!$D$6:$D$605,Compras!$B$6:$B$605,$A13,Compras!$C$6:$C$605,"Grande")-SUMIFS(Ventas!$D$6:$D$605,Ventas!$B$6:$B$605,$A13,Ventas!$C$6:$C$605,"Grande"),"")) | H13: =IF($A13="","",N($D13)+N($E13)+N($F13)+N($G13)) -> 1 | I13: =IF($A13="","",IF(N($H13)<=0,"SIN STOCK",IF(LEFT($C13,6)="Anillo",IF(IF(AND(SUMIFS(Compras!$D$6:$D$605,Compras!$B$6:$B$605,$A13,Compras!$C$6:$C$605,"Chico")>0,N($E13)<=$B$5),"C ","")&IF(AND(SUMIFS(Compras!$D$6:$D$605,Compras!$B$6:$B$605,$A13,Compras!$C$6:$C$605,"Mediano")>0,N($F13)<=$B$5),"M ","")&IF(AND(SUMIFS(Compras!$D$6:$D$605,Compras!$B$6:$B$605,$A13,Compras!$C$6:$C$605,"Grande")>0,N($G13)<=$B$5),"G","")="","","Reponer "&IF(AND(SUMIFS(Compras!$D$6:$D$605,Compras!$B$6:$B$605,$A13,Compras!$C$6:$C$605,"Chico")>0,N($E13)<=$B$5),"C ","")&IF(AND(SUMIFS(Compras!$D$6:$D$605,Compras!$B$6:$B$605,$A13,Compras!$C$6:$C$605,"Mediano")>0,N($F13)<=$B$5),"M ","")&IF(AND(SUMIFS(Compras!$D$6:$D$605,Compras!$B$6:$B$605,$A13,Compras!$C$6:$C$605,"Grande")>0,N($G13)<=$B$5),"G","")),IF(N($H13)<=$B$5,"REPONER","")))) -> REPONER | J13: =IF($A13="","",SUMIFS(Ventas!$D$6:$D$605,Ventas!$B$6:$B$605,$A13)) -> 1 | K13: =IF($A13="","",SUMIFS(Ventas!$F$6:$F$605,Ventas!$B$6:$B$605,$A13)) -> 9000
A14: =IF(Costos!$A28="","",Costos!$A28) -> Cubic Mini Circulo | B14: =IF(Costos!$A28="","",Costos!$B28&"") -> Plata 925 | C14: =IF(Costos!$A28="","",Costos!$C28&"") -> Aros | D14: =IF($A14="","",SUMIFS(Compras!$D$6:$D$605,Compras!$B$6:$B$605,$A14,Compras!$C$6:$C$605,"Único")-SUMIFS(Ventas!$D$6:$D$605,Ventas!$B$6:$B$605,$A14,Ventas!$C$6:$C$605,"Único")) -> 0 | E14: =IF($A14="","",IF(LEFT($C14,6)="Anillo",SUMIFS(Compras!$D$6:$D$605,Compras!$B$6:$B$605,$A14,Compras!$C$6:$C$605,"Chico")-SUMIFS(Ventas!$D$6:$D$605,Ventas!$B$6:$B$605,$A14,Ventas!$C$6:$C$605,"Chico"),"")) | F14: =IF($A14="","",IF(LEFT($C14,6)="Anillo",SUMIFS(Compras!$D$6:$D$605,Compras!$B$6:$B$605,$A14,Compras!$C$6:$C$605,"Mediano")-SUMIFS(Ventas!$D$6:$D$605,Ventas!$B$6:$B$605,$A14,Ventas!$C$6:$C$605,"Mediano"),"")) | G14: =IF($A14="","",IF(LEFT($C14,6)="Anillo",SUMIFS(Compras!$D$6:$D$605,Compras!$B$6:$B$605,$A14,Compras!$C$6:$C$605,"Grande")-SUMIFS(Ventas!$D$6:$D$605,Ventas!$B$6:$B$605,$A14,Ventas!$C$6:$C$605,"Grande"),"")) | H14: =IF($A14="","",N($D14)+N($E14)+N($F14)+N($G14)) -> 0 | I14: =IF($A14="","",IF(N($H14)<=0,"SIN STOCK",IF(LEFT($C14,6)="Anillo",IF(IF(AND(SUMIFS(Compras!$D$6:$D$605,Compras!$B$6:$B$605,$A14,Compras!$C$6:$C$605,"Chico")>0,N($E14)<=$B$5),"C ","")&IF(AND(SUMIFS(Compras!$D$6:$D$605,Compras!$B$6:$B$605,$A14,Compras!$C$6:$C$605,"Mediano")>0,N($F14)<=$B$5),"M ","")&IF(AND(SUMIFS(Compras!$D$6:$D$605,Compras!$B$6:$B$605,$A14,Compras!$C$6:$C$605,"Grande")>0,N($G14)<=$B$5),"G","")="","","Reponer "&IF(AND(SUMIFS(Compras!$D$6:$D$605,Compras!$B$6:$B$605,$A14,Compras!$C$6:$C$605,"Chico")>0,N($E14)<=$B$5),"C ","")&IF(AND(SUMIFS(Compras!$D$6:$D$605,Compras!$B$6:$B$605,$A14,Compras!$C$6:$C$605,"Mediano")>0,N($F14)<=$B$5),"M ","")&IF(AND(SUMIFS(Compras!$D$6:$D$605,Compras!$B$6:$B$605,$A14,Compras!$C$6:$C$605,"Grande")>0,N($G14)<=$B$5),"G","")),IF(N($H14)<=$B$5,"REPONER","")))) -> SIN STOCK | J14: =IF($A14="","",SUMIFS(Ventas!$D$6:$D$605,Ventas!$B$6:$B$605,$A14)) -> 1 | K14: =IF($A14="","",SUMIFS(Ventas!$F$6:$F$605,Ventas!$B$6:$B$605,$A14)) -> 12000
A15: =IF(Costos!$A29="","",Costos!$A29) -> Cubic Circulo Docha | B15: =IF(Costos!$A29="","",Costos!$B29&"") -> Plata 925 | C15: =IF(Costos!$A29="","",Costos!$C29&"") -> Aros | D15: =IF($A15="","",SUMIFS(Compras!$D$6:$D$605,Compras!$B$6:$B$605,$A15,Compras!$C$6:$C$605,"Único")-SUMIFS(Ventas!$D$6:$D$605,Ventas!$B$6:$B$605,$A15,Ventas!$C$6:$C$605,"Único")) -> 0 | E15: =IF($A15="","",IF(LEFT($C15,6)="Anillo",SUMIFS(Compras!$D$6:$D$605,Compras!$B$6:$B$605,$A15,Compras!$C$6:$C$605,"Chico")-SUMIFS(Ventas!$D$6:$D$605,Ventas!$B$6:$B$605,$A15,Ventas!$C$6:$C$605,"Chico"),"")) | F15: =IF($A15="","",IF(LEFT($C15,6)="Anillo",SUMIFS(Compras!$D$6:$D$605,Compras!$B$6:$B$605,$A15,Compras!$C$6:$C$605,"Mediano")-SUMIFS(Ventas!$D$6:$D$605,Ventas!$B$6:$B$605,$A15,Ventas!$C$6:$C$605,"Mediano"),"")) | G15: =IF($A15="","",IF(LEFT($C15,6)="Anillo",SUMIFS(Compras!$D$6:$D$605,Compras!$B$6:$B$605,$A15,Compras!$C$6:$C$605,"Grande")-SUMIFS(Ventas!$D$6:$D$605,Ventas!$B$6:$B$605,$A15,Ventas!$C$6:$C$605,"Grande"),"")) | H15: =IF($A15="","",N($D15)+N($E15)+N($F15)+N($G15)) -> 0 | I15: =IF($A15="","",IF(N($H15)<=0,"SIN STOCK",IF(LEFT($C15,6)="Anillo",IF(IF(AND(SUMIFS(Compras!$D$6:$D$605,Compras!$B$6:$B$605,$A15,Compras!$C$6:$C$605,"Chico")>0,N($E15)<=$B$5),"C ","")&IF(AND(SUMIFS(Compras!$D$6:$D$605,Compras!$B$6:$B$605,$A15,Compras!$C$6:$C$605,"Mediano")>0,N($F15)<=$B$5),"M ","")&IF(AND(SUMIFS(Compras!$D$6:$D$605,Compras!$B$6:$B$605,$A15,Compras!$C$6:$C$605,"Grande")>0,N($G15)<=$B$5),"G","")="","","Reponer "&IF(AND(SUMIFS(Compras!$D$6:$D$605,Compras!$B$6:$B$605,$A15,Compras!$C$6:$C$605,"Chico")>0,N($E15)<=$B$5),"C ","")&IF(AND(SUMIFS(Compras!$D$6:$D$605,Compras!$B$6:$B$605,$A15,Compras!$C$6:$C$605,"Mediano")>0,N($F15)<=$B$5),"M ","")&IF(AND(SUMIFS(Compras!$D$6:$D$605,Compras!$B$6:$B$605,$A15,Compras!$C$6:$C$605,"Grande")>0,N($G15)<=$B$5),"G","")),IF(N($H15)<=$B$5,"REPONER","")))) -> SIN STOCK | J15: =IF($A15="","",SUMIFS(Ventas!$D$6:$D$605,Ventas!$B$6:$B$605,$A15)) -> 1 | K15: =IF($A15="","",SUMIFS(Ventas!$F$6:$F$605,Ventas!$B$6:$B$605,$A15)) -> 12500
A16: =IF(Costos!$A30="","",Costos!$A30) -> Cubic Cuadrado | B16: =IF(Costos!$A30="","",Costos!$B30&"") -> Plata 925 | C16: =IF(Costos!$A30="","",Costos!$C30&"") -> Aros | D16: =IF($A16="","",SUMIFS(Compras!$D$6:$D$605,Compras!$B$6:$B$605,$A16,Compras!$C$6:$C$605,"Único")-SUMIFS(Ventas!$D$6:$D$605,Ventas!$B$6:$B$605,$A16,Ventas!$C$6:$C$605,"Único")) -> 0 | E16: =IF($A16="","",IF(LEFT($C16,6)="Anillo",SUMIFS(Compras!$D$6:$D$605,Compras!$B$6:$B$605,$A16,Compras!$C$6:$C$605,"Chico")-SUMIFS(Ventas!$D$6:$D$605,Ventas!$B$6:$B$605,$A16,Ventas!$C$6:$C$605,"Chico"),"")) | F16: =IF($A16="","",IF(LEFT($C16,6)="Anillo",SUMIFS(Compras!$D$6:$D$605,Compras!$B$6:$B$605,$A16,Compras!$C$6:$C$605,"Mediano")-SUMIFS(Ventas!$D$6:$D$605,Ventas!$B$6:$B$605,$A16,Ventas!$C$6:$C$605,"Mediano"),"")) | G16: =IF($A16="","",IF(LEFT($C16,6)="Anillo",SUMIFS(Compras!$D$6:$D$605,Compras!$B$6:$B$605,$A16,Compras!$C$6:$C$605,"Grande")-SUMIFS(Ventas!$D$6:$D$605,Ventas!$B$6:$B$605,$A16,Ventas!$C$6:$C$605,"Grande"),"")) | H16: =IF($A16="","",N($D16)+N($E16)+N($F16)+N($G16)) -> 0 | I16: =IF($A16="","",IF(N($H16)<=0,"SIN STOCK",IF(LEFT($C16,6)="Anillo",IF(IF(AND(SUMIFS(Compras!$D$6:$D$605,Compras!$B$6:$B$605,$A16,Compras!$C$6:$C$605,"Chico")>0,N($E16)<=$B$5),"C ","")&IF(AND(SUMIFS(Compras!$D$6:$D$605,Compras!$B$6:$B$605,$A16,Compras!$C$6:$C$605,"Mediano")>0,N($F16)<=$B$5),"M ","")&IF(AND(SUMIFS(Compras!$D$6:$D$605,Compras!$B$6:$B$605,$A16,Compras!$C$6:$C$605,"Grande")>0,N($G16)<=$B$5),"G","")="","","Reponer "&IF(AND(SUMIFS(Compras!$D$6:$D$605,Compras!$B$6:$B$605,$A16,Compras!$C$6:$C$605,"Chico")>0,N($E16)<=$B$5),"C ","")&IF(AND(SUMIFS(Compras!$D$6:$D$605,Compras!$B$6:$B$605,$A16,Compras!$C$6:$C$605,"Mediano")>0,N($F16)<=$B$5),"M ","")&IF(AND(SUMIFS(Compras!$D$6:$D$605,Compras!$B$6:$B$605,$A16,Compras!$C$6:$C$605,"Grande")>0,N($G16)<=$B$5),"G","")),IF(N($H16)<=$B$5,"REPONER","")))) -> SIN STOCK | J16: =IF($A16="","",SUMIFS(Ventas!$D$6:$D$605,Ventas!$B$6:$B$605,$A16)) -> 1 | K16: =IF($A16="","",SUMIFS(Ventas!$F$6:$F$605,Ventas!$B$6:$B$605,$A16)) -> 12500
A17: =IF(Costos!$A31="","",Costos!$A31) -> Argollitas Marco Docha | B17: =IF(Costos!$A31="","",Costos!$B31&"") -> Plata 925 | C17: =IF(Costos!$A31="","",Costos!$C31&"") -> Aros | D17: =IF($A17="","",SUMIFS(Compras!$D$6:$D$605,Compras!$B$6:$B$605,$A17,Compras!$C$6:$C$605,"Único")-SUMIFS(Ventas!$D$6:$D$605,Ventas!$B$6:$B$605,$A17,Ventas!$C$6:$C$605,"Único")) -> 0 | E17: =IF($A17="","",IF(LEFT($C17,6)="Anillo",SUMIFS(Compras!$D$6:$D$605,Compras!$B$6:$B$605,$A17,Compras!$C$6:$C$605,"Chico")-SUMIFS(Ventas!$D$6:$D$605,Ventas!$B$6:$B$605,$A17,Ventas!$C$6:$C$605,"Chico"),"")) | F17: =IF($A17="","",IF(LEFT($C17,6)="Anillo",SUMIFS(Compras!$D$6:$D$605,Compras!$B$6:$B$605,$A17,Compras!$C$6:$C$605,"Mediano")-SUMIFS(Ventas!$D$6:$D$605,Ventas!$B$6:$B$605,$A17,Ventas!$C$6:$C$605,"Mediano"),"")) | G17: =IF($A17="","",IF(LEFT($C17,6)="Anillo",SUMIFS(Compras!$D$6:$D$605,Compras!$B$6:$B$605,$A17,Compras!$C$6:$C$605,"Grande")-SUMIFS(Ventas!$D$6:$D$605,Ventas!$B$6:$B$605,$A17,Ventas!$C$6:$C$605,"Grande"),"")) | H17: =IF($A17="","",N($D17)+N($E17)+N($F17)+N($G17)) -> 0 | I17: =IF($A17="","",IF(N($H17)<=0,"SIN STOCK",IF(LEFT($C17,6)="Anillo",IF(IF(AND(SUMIFS(Compras!$D$6:$D$605,Compras!$B$6:$B$605,$A17,Compras!$C$6:$C$605,"Chico")>0,N($E17)<=$B$5),"C ","")&IF(AND(SUMIFS(Compras!$D$6:$D$605,Compras!$B$6:$B$605,$A17,Compras!$C$6:$C$605,"Mediano")>0,N($F17)<=$B$5),"M ","")&IF(AND(SUMIFS(Compras!$D$6:$D$605,Compras!$B$6:$B$605,$A17,Compras!$C$6:$C$605,"Grande")>0,N($G17)<=$B$5),"G","")="","","Reponer "&IF(AND(SUMIFS(Compras!$D$6:$D$605,Compras!$B$6:$B$605,$A17,Compras!$C$6:$C$605,"Chico")>0,N($E17)<=$B$5),"C ","")&IF(AND(SUMIFS(Compras!$D$6:$D$605,Compras!$B$6:$B$605,$A17,Compras!$C$6:$C$605,"Mediano")>0,N($F17)<=$B$5),"M ","")&IF(AND(SUMIFS(Compras!$D$6:$D$605,Compras!$B$6:$B$605,$A17,Compras!$C$6:$C$605,"Grande")>0,N($G17)<=$B$5),"G","")),IF(N($H17)<=$B$5,"REPONER","")))) -> SIN STOCK | J17: =IF($A17="","",SUMIFS(Ventas!$D$6:$D$605,Ventas!$B$6:$B$605,$A17)) -> 1 | K17: =IF($A17="","",SUMIFS(Ventas!$F$6:$F$605,Ventas!$B$6:$B$605,$A17)) -> 25000
A18: =IF(Costos!$A32="","",Costos!$A32) -> Anillo Circulo | B18: =IF(Costos!$A32="","",Costos!$B32&"") -> Plata 925 | C18: =IF(Costos!$A32="","",Costos!$C32&"") -> Anillo | D18: =IF($A18="","",SUMIFS(Compras!$D$6:$D$605,Compras!$B$6:$B$605,$A18,Compras!$C$6:$C$605,"Único")-SUMIFS(Ventas!$D$6:$D$605,Ventas!$B$6:$B$605,$A18,Ventas!$C$6:$C$605,"Único")) -> 0 | E18: =IF($A18="","",IF(LEFT($C18,6)="Anillo",SUMIFS(Compras!$D$6:$D$605,Compras!$B$6:$B$605,$A18,Compras!$C$6:$C$605,"Chico")-SUMIFS(Ventas!$D$6:$D$605,Ventas!$B$6:$B$605,$A18,Ventas!$C$6:$C$605,"Chico"),"")) -> 0 | F18: =IF($A18="","",IF(LEFT($C18,6)="Anillo",SUMIFS(Compras!$D$6:$D$605,Compras!$B$6:$B$605,$A18,Compras!$C$6:$C$605,"Mediano")-SUMIFS(Ventas!$D$6:$D$605,Ventas!$B$6:$B$605,$A18,Ventas!$C$6:$C$605,"Mediano"),"")) -> 0 | G18: =IF($A18="","",IF(LEFT($C18,6)="Anillo",SUMIFS(Compras!$D$6:$D$605,Compras!$B$6:$B$605,$A18,Compras!$C$6:$C$605,"Grande")-SUMIFS(Ventas!$D$6:$D$605,Ventas!$B$6:$B$605,$A18,Ventas!$C$6:$C$605,"Grande"),"")) -> 0 | H18: =IF($A18="","",N($D18)+N($E18)+N($F18)+N($G18)) -> 0 | I18: =IF($A18="","",IF(N($H18)<=0,"SIN STOCK",IF(LEFT($C18,6)="Anillo",IF(IF(AND(SUMIFS(Compras!$D$6:$D$605,Compras!$B$6:$B$605,$A18,Compras!$C$6:$C$605,"Chico")>0,N($E18)<=$B$5),"C ","")&IF(AND(SUMIFS(Compras!$D$6:$D$605,Compras!$B$6:$B$605,$A18,Compras!$C$6:$C$605,"Mediano")>0,N($F18)<=$B$5),"M ","")&IF(AND(SUMIFS(Compras!$D$6:$D$605,Compras!$B$6:$B$605,$A18,Compras!$C$6:$C$605,"Grande")>0,N($G18)<=$B$5),"G","")="","","Reponer "&IF(AND(SUMIFS(Compras!$D$6:$D$605,Compras!$B$6:$B$605,$A18,Compras!$C$6:$C$605,"Chico")>0,N($E18)<=$B$5),"C ","")&IF(AND(SUMIFS(Compras!$D$6:$D$605,Compras!$B$6:$B$605,$A18,Compras!$C$6:$C$605,"Mediano")>0,N($F18)<=$B$5),"M ","")&IF(AND(SUMIFS(Compras!$D$6:$D$605,Compras!$B$6:$B$605,$A18,Compras!$C$6:$C$605,"Grande")>0,N($G18)<=$B$5),"G","")),IF(N($H18)<=$B$5,"REPONER","")))) -> SIN STOCK | J18: =IF($A18="","",SUMIFS(Ventas!$D$6:$D$605,Ventas!$B$6:$B$605,$A18)) -> 2 | K18: =IF($A18="","",SUMIFS(Ventas!$F$6:$F$605,Ventas!$B$6:$B$605,$A18)) -> 32000
A19: =IF(Costos!$A33="","",Costos!$A33) -> Anillo Gota | B19: =IF(Costos!$A33="","",Costos!$B33&"") -> Plata 925 | C19: =IF(Costos!$A33="","",Costos!$C33&"") -> Anillo | D19: =IF($A19="","",SUMIFS(Compras!$D$6:$D$605,Compras!$B$6:$B$605,$A19,Compras!$C$6:$C$605,"Único")-SUMIFS(Ventas!$D$6:$D$605,Ventas!$B$6:$B$605,$A19,Ventas!$C$6:$C$605,"Único")) -> 0 | E19: =IF($A19="","",IF(LEFT($C19,6)="Anillo",SUMIFS(Compras!$D$6:$D$605,Compras!$B$6:$B$605,$A19,Compras!$C$6:$C$605,"Chico")-SUMIFS(Ventas!$D$6:$D$605,Ventas!$B$6:$B$605,$A19,Ventas!$C$6:$C$605,"Chico"),"")) -> 0 | F19: =IF($A19="","",IF(LEFT($C19,6)="Anillo",SUMIFS(Compras!$D$6:$D$605,Compras!$B$6:$B$605,$A19,Compras!$C$6:$C$605,"Mediano")-SUMIFS(Ventas!$D$6:$D$605,Ventas!$B$6:$B$605,$A19,Ventas!$C$6:$C$605,"Mediano"),"")) -> 0 | G19: =IF($A19="","",IF(LEFT($C19,6)="Anillo",SUMIFS(Compras!$D$6:$D$605,Compras!$B$6:$B$605,$A19,Compras!$C$6:$C$605,"Grande")-SUMIFS(Ventas!$D$6:$D$605,Ventas!$B$6:$B$605,$A19,Ventas!$C$6:$C$605,"Grande"),"")) -> 0 | H19: =IF($A19="","",N($D19)+N($E19)+N($F19)+N($G19)) -> 0 | I19: =IF($A19="","",IF(N($H19)<=0,"SIN STOCK",IF(LEFT($C19,6)="Anillo",IF(IF(AND(SUMIFS(Compras!$D$6:$D$605,Compras!$B$6:$B$605,$A19,Compras!$C$6:$C$605,"Chico")>0,N($E19)<=$B$5),"C ","")&IF(AND(SUMIFS(Compras!$D$6:$D$605,Compras!$B$6:$B$605,$A19,Compras!$C$6:$C$605,"Mediano")>0,N($F19)<=$B$5),"M ","")&IF(AND(SUMIFS(Compras!$D$6:$D$605,Compras!$B$6:$B$605,$A19,Compras!$C$6:$C$605,"Grande")>0,N($G19)<=$B$5),"G","")="","","Reponer "&IF(AND(SUMIFS(Compras!$D$6:$D$605,Compras!$B$6:$B$605,$A19,Compras!$C$6:$C$605,"Chico")>0,N($E19)<=$B$5),"C ","")&IF(AND(SUMIFS(Compras!$D$6:$D$605,Compras!$B$6:$B$605,$A19,Compras!$C$6:$C$605,"Mediano")>0,N($F19)<=$B$5),"M ","")&IF(AND(SUMIFS(Compras!$D$6:$D$605,Compras!$B$6:$B$605,$A19,Compras!$C$6:$C$605,"Grande")>0,N($G19)<=$B$5),"G","")),IF(N($H19)<=$B$5,"REPONER","")))) -> SIN STOCK | J19: =IF($A19="","",SUMIFS(Ventas!$D$6:$D$605,Ventas!$B$6:$B$605,$A19)) -> 1 | K19: =IF($A19="","",SUMIFS(Ventas!$F$6:$F$605,Ventas!$B$6:$B$605,$A19)) -> 23000
A20: =IF(Costos!$A34="","",Costos!$A34) -> Anillo Vera Docha | B20: =IF(Costos!$A34="","",Costos!$B34&"") -> Plata 925 | C20: =IF(Costos!$A34="","",Costos!$C34&"") -> Anillo | D20: =IF($A20="","",SUMIFS(Compras!$D$6:$D$605,Compras!$B$6:$B$605,$A20,Compras!$C$6:$C$605,"Único")-SUMIFS(Ventas!$D$6:$D$605,Ventas!$B$6:$B$605,$A20,Ventas!$C$6:$C$605,"Único")) -> 0 | E20: =IF($A20="","",IF(LEFT($C20,6)="Anillo",SUMIFS(Compras!$D$6:$D$605,Compras!$B$6:$B$605,$A20,Compras!$C$6:$C$605,"Chico")-SUMIFS(Ventas!$D$6:$D$605,Ventas!$B$6:$B$605,$A20,Ventas!$C$6:$C$605,"Chico"),"")) -> 0 | F20: =IF($A20="","",IF(LEFT($C20,6)="Anillo",SUMIFS(Compras!$D$6:$D$605,Compras!$B$6:$B$605,$A20,Compras!$C$6:$C$605,"Mediano")-SUMIFS(Ventas!$D$6:$D$605,Ventas!$B$6:$B$605,$A20,Ventas!$C$6:$C$605,"Mediano"),"")) -> 0 | G20: =IF($A20="","",IF(LEFT($C20,6)="Anillo",SUMIFS(Compras!$D$6:$D$605,Compras!$B$6:$B$605,$A20,Compras!$C$6:$C$605,"Grande")-SUMIFS(Ventas!$D$6:$D$605,Ventas!$B$6:$B$605,$A20,Ventas!$C$6:$C$605,"Grande"),"")) -> 1 | H20: =IF($A20="","",N($D20)+N($E20)+N($F20)+N($G20)) -> 1 | I20: =IF($A20="","",IF(N($H20)<=0,"SIN STOCK",IF(LEFT($C20,6)="Anillo",IF(IF(AND(SUMIFS(Compras!$D$6:$D$605,Compras!$B$6:$B$605,$A20,Compras!$C$6:$C$605,"Chico")>0,N($E20)<=$B$5),"C ","")&IF(AND(SUMIFS(Compras!$D$6:$D$605,Compras!$B$6:$B$605,$A20,Compras!$C$6:$C$605,"Mediano")>0,N($F20)<=$B$5),"M ","")&IF(AND(SUMIFS(Compras!$D$6:$D$605,Compras!$B$6:$B$605,$A20,Compras!$C$6:$C$605,"Grande")>0,N($G20)<=$B$5),"G","")="","","Reponer "&IF(AND(SUMIFS(Compras!$D$6:$D$605,Compras!$B$6:$B$605,$A20,Compras!$C$6:$C$605,"Chico")>0,N($E20)<=$B$5),"C ","")&IF(AND(SUMIFS(Compras!$D$6:$D$605,Compras!$B$6:$B$605,$A20,Compras!$C$6:$C$605,"Mediano")>0,N($F20)<=$B$5),"M ","")&IF(AND(SUMIFS(Compras!$D$6:$D$605,Compras!$B$6:$B$605,$A20,Compras!$C$6:$C$605,"Grande")>0,N($G20)<=$B$5),"G","")),IF(N($H20)<=$B$5,"REPONER","")))) -> Reponer G | J20: =IF($A20="","",SUMIFS(Ventas!$D$6:$D$605,Ventas!$B$6:$B$605,$A20)) -> 0 | K20: =IF($A20="","",SUMIFS(Ventas!$F$6:$F$605,Ventas!$B$6:$B$605,$A20)) -> 0
... A136: =IF(Costos!$A150="","",Costos!$A150) | B136: =IF(Costos!$A150="","",Costos!$B150&"") | C136: =IF(Costos!$A150="","",Costos!$C150&"") | D136: =IF($A136="","",SUMIFS(Compras!$D$6:$D$605,Compras!$B$6:$B$605,$A136,Compras!$C$6:$C$605,"Único")-SUMIFS(Ventas!$D$6:$D$605,Ventas!$B$6:$B$605,$A136,Ventas!$C$6:$C$605,"Único")) | E136: =IF($A136="","",IF(LEFT($C136,6)="Anillo",SUMIFS(Compras!$D$6:$D$605,Compras!$B$6:$B$605,$A136,Compras!$C$6:$C$605,"Chico")-SUMIFS(Ventas!$D$6:$D$605,Ventas!$B$6:$B$605,$A136,Ventas!$C$6:$C$605,"Chico"),"")) | F136: =IF($A136="","",IF(LEFT($C136,6)="Anillo",SUMIFS(Compras!$D$6:$D$605,Compras!$B$6:$B$605,$A136,Compras!$C$6:$C$605,"Mediano")-SUMIFS(Ventas!$D$6:$D$605,Ventas!$B$6:$B$605,$A136,Ventas!$C$6:$C$605,"Mediano"),"")) | G136: =IF($A136="","",IF(LEFT($C136,6)="Anillo",SUMIFS(Compras!$D$6:$D$605,Compras!$B$6:$B$605,$A136,Compras!$C$6:$C$605,"Grande")-SUMIFS(Ventas!$D$6:$D$605,Ventas!$B$6:$B$605,$A136,Ventas!$C$6:$C$605,"Grande"),"")) | H136: =IF($A136="","",N($D136)+N($E136)+N($F136)+N($G136)) | I136: =IF($A136="","",IF(N($H136)<=0,"SIN STOCK",IF(LEFT($C136,6)="Anillo",IF(IF(AND(SUMIFS(Compras!$D$6:$D$605,Compras!$B$6:$B$605,$A136,Compras!$C$6:$C$605,"Chico")>0,N($E136)<=$B$5),"C ","")&IF(AND(SUMIFS(Compras!$D$6:$D$605,Compras!$B$6:$B$605,$A136,Compras!$C$6:$C$605,"Mediano")>0,N($F136)<=$B$5),"M ","")&IF(AND(SUMIFS(Compras!$D$6:$D$605,Compras!$B$6:$B$605,$A136,Compras!$C$6:$C$605,"Grande")>0,N($G136)<=$B$5),"G","")="","","Reponer "&IF(AND(SUMIFS(Compras!$D$6:$D$605,Compras!$B$6:$B$605,$A136,Compras!$C$6:$C$605,"Chico")>0,N($E136)<=$B$5),"C ","")&IF(AND(SUMIFS(Compras!$D$6:$D$605,Compras!$B$6:$B$605,$A136,Compras!$C$6:$C$605,"Mediano")>0,N($F136)<=$B$5),"M ","")&IF(AND(SUMIFS(Compras!$D$6:$D$605,Compras!$B$6:$B$605,$A136,Compras!$C$6:$C$605,"Grande")>0,N($G136)<=$B$5),"G","")),IF(N($H136)<=$B$5,"REPONER","")))) | J136: =IF($A136="","",SUMIFS(Ventas!$D$6:$D$605,Ventas!$B$6:$B$605,$A136)) | K136: =IF($A136="","",SUMIFS(Ventas!$F$6:$F$605,Ventas!$B$6:$B$605,$A136))
A145: Cómo leer esta hoja
A146: • Todo sale de Compras y Ventas. La única celda editable acá es el aviso de B5.
A147: • Estado dice SIN STOCK cuando no queda nada y REPONER cuando quedan pocas.
A148: • En anillos, Reponer nombra solo los talles que alguna vez compraste.

Sheet Web
A1: DATOS PARA LA WEB
A2: Esta hoja se completa sola desde Costos y Stock. No cargues nada acá salvo la columna Destacado y la de Foto.
A3: Es la única hoja que se publica: no incluye costos, proveedores ni márgenes.
A5: Producto | B5: Material | C5: Categoría | D5: Precio | E5: Stock | F5: Chico | G5: Mediano | H5: Grande | I5: Destacado | J5: Foto (link) | K5: Vendidas
A6: =IF(Costos!$A23="","",Costos!$A23) -> Argollitas Classic N°1 | B6: =IF(Costos!$A23="","",Costos!$B23&"") -> Plata 925 | C6: =IF(Costos!$A23="","",Costos!$C23&"") -> Aros | D6: =IF(Costos!$A23="","",N(Costos!$K23)) -> 7000 | E6: =IF(Costos!$A23="","",N(Stock!$H9)) -> 0 | F6: =IF(Costos!$A23="","",N(Stock!$E9)+IF(LEFT(Stock!$C9,6)="Anillo",0,N(Stock!$D9))) -> 0 | G6: =IF(Costos!$A23="","",N(Stock!$F9)) -> 0 | H6: =IF(Costos!$A23="","",N(Stock!$G9)) -> 0 | K6: =IF(Costos!$A23="","",N(Stock!$J9)) -> 1
A7: =IF(Costos!$A24="","",Costos!$A24) -> Argollitas Classic N°2 | B7: =IF(Costos!$A24="","",Costos!$B24&"") -> Plata 925 | C7: =IF(Costos!$A24="","",Costos!$C24&"") -> Aros | D7: =IF(Costos!$A24="","",N(Costos!$K24)) -> 7500 | E7: =IF(Costos!$A24="","",N(Stock!$H10)) -> 0 | F7: =IF(Costos!$A24="","",N(Stock!$E10)+IF(LEFT(Stock!$C10,6)="Anillo",0,N(Stock!$D10))) -> 0 | G7: =IF(Costos!$A24="","",N(Stock!$F10)) -> 0 | H7: =IF(Costos!$A24="","",N(Stock!$G10)) -> 0 | K7: =IF(Costos!$A24="","",N(Stock!$J10)) -> 1
A8: =IF(Costos!$A25="","",Costos!$A25) -> Argollitas Classic N°3 | B8: =IF(Costos!$A25="","",Costos!$B25&"") -> Plata 925 | C8: =IF(Costos!$A25="","",Costos!$C25&"") -> Aros | D8: =IF(Costos!$A25="","",N(Costos!$K25)) -> 8000 | E8: =IF(Costos!$A25="","",N(Stock!$H11)) -> 0 | F8: =IF(Costos!$A25="","",N(Stock!$E11)+IF(LEFT(Stock!$C11,6)="Anillo",0,N(Stock!$D11))) -> 0 | G8: =IF(Costos!$A25="","",N(Stock!$F11)) -> 0 | H8: =IF(Costos!$A25="","",N(Stock!$G11)) -> 0 | K8: =IF(Costos!$A25="","",N(Stock!$J11)) -> 1
A9: =IF(Costos!$A26="","",Costos!$A26) -> Argollitas Classic N°4 | B9: =IF(Costos!$A26="","",Costos!$B26&"") -> Plata 925 | C9: =IF(Costos!$A26="","",Costos!$C26&"") -> Aros | D9: =IF(Costos!$A26="","",N(Costos!$K26)) -> 8500 | E9: =IF(Costos!$A26="","",N(Stock!$H12)) -> 0 | F9: =IF(Costos!$A26="","",N(Stock!$E12)+IF(LEFT(Stock!$C12,6)="Anillo",0,N(Stock!$D12))) -> 0 | G9: =IF(Costos!$A26="","",N(Stock!$F12)) -> 0 | H9: =IF(Costos!$A26="","",N(Stock!$G12)) -> 0 | K9: =IF(Costos!$A26="","",N(Stock!$J12)) -> 1
A10: =IF(Costos!$A27="","",Costos!$A27) -> Argollitas Classic N°5 | B10: =IF(Costos!$A27="","",Costos!$B27&"") -> Plata 925 | C10: =IF(Costos!$A27="","",Costos!$C27&"") -> Aros | D10: =IF(Costos!$A27="","",N(Costos!$K27)) -> 9000 | E10: =IF(Costos!$A27="","",N(Stock!$H13)) -> 1 | F10: =IF(Costos!$A27="","",N(Stock!$E13)+IF(LEFT(Stock!$C13,6)="Anillo",0,N(Stock!$D13))) -> 1 | G10: =IF(Costos!$A27="","",N(Stock!$F13)) -> 0 | H10: =IF(Costos!$A27="","",N(Stock!$G13)) -> 0 | K10: =IF(Costos!$A27="","",N(Stock!$J13)) -> 1
A11: =IF(Costos!$A28="","",Costos!$A28) -> Cubic Mini Circulo | B11: =IF(Costos!$A28="","",Costos!$B28&"") -> Plata 925 | C11: =IF(Costos!$A28="","",Costos!$C28&"") -> Aros | D11: =IF(Costos!$A28="","",N(Costos!$K28)) -> 12000 | E11: =IF(Costos!$A28="","",N(Stock!$H14)) -> 0 | F11: =IF(Costos!$A28="","",N(Stock!$E14)+IF(LEFT(Stock!$C14,6)="Anillo",0,N(Stock!$D14))) -> 0 | G11: =IF(Costos!$A28="","",N(Stock!$F14)) -> 0 | H11: =IF(Costos!$A28="","",N(Stock!$G14)) -> 0 | K11: =IF(Costos!$A28="","",N(Stock!$J14)) -> 1
A12: =IF(Costos!$A29="","",Costos!$A29) -> Cubic Circulo Docha | B12: =IF(Costos!$A29="","",Costos!$B29&"") -> Plata 925 | C12: =IF(Costos!$A29="","",Costos!$C29&"") -> Aros | D12: =IF(Costos!$A29="","",N(Costos!$K29)) -> 12500 | E12: =IF(Costos!$A29="","",N(Stock!$H15)) -> 0 | F12: =IF(Costos!$A29="","",N(Stock!$E15)+IF(LEFT(Stock!$C15,6)="Anillo",0,N(Stock!$D15))) -> 0 | G12: =IF(Costos!$A29="","",N(Stock!$F15)) -> 0 | H12: =IF(Costos!$A29="","",N(Stock!$G15)) -> 0 | K12: =IF(Costos!$A29="","",N(Stock!$J15)) -> 1
A13: =IF(Costos!$A30="","",Costos!$A30) -> Cubic Cuadrado | B13: =IF(Costos!$A30="","",Costos!$B30&"") -> Plata 925 | C13: =IF(Costos!$A30="","",Costos!$C30&"") -> Aros | D13: =IF(Costos!$A30="","",N(Costos!$K30)) -> 12500 | E13: =IF(Costos!$A30="","",N(Stock!$H16)) -> 0 | F13: =IF(Costos!$A30="","",N(Stock!$E16)+IF(LEFT(Stock!$C16,6)="Anillo",0,N(Stock!$D16))) -> 0 | G13: =IF(Costos!$A30="","",N(Stock!$F16)) -> 0 | H13: =IF(Costos!$A30="","",N(Stock!$G16)) -> 0 | K13: =IF(Costos!$A30="","",N(Stock!$J16)) -> 1
A14: =IF(Costos!$A31="","",Costos!$A31) -> Argollitas Marco Docha | B14: =IF(Costos!$A31="","",Costos!$B31&"") -> Plata 925 | C14: =IF(Costos!$A31="","",Costos!$C31&"") -> Aros | D14: =IF(Costos!$A31="","",N(Costos!$K31)) -> 25000 | E14: =IF(Costos!$A31="","",N(Stock!$H17)) -> 0 | F14: =IF(Costos!$A31="","",N(Stock!$E17)+IF(LEFT(Stock!$C17,6)="Anillo",0,N(Stock!$D17))) -> 0 | G14: =IF(Costos!$A31="","",N(Stock!$F17)) -> 0 | H14: =IF(Costos!$A31="","",N(Stock!$G17)) -> 0 | K14: =IF(Costos!$A31="","",N(Stock!$J17)) -> 1
A15: =IF(Costos!$A32="","",Costos!$A32) -> Anillo Circulo | B15: =IF(Costos!$A32="","",Costos!$B32&"") -> Plata 925 | C15: =IF(Costos!$A32="","",Costos!$C32&"") -> Anillo | D15: =IF(Costos!$A32="","",N(Costos!$K32)) -> 16000 | E15: =IF(Costos!$A32="","",N(Stock!$H18)) -> 0 | F15: =IF(Costos!$A32="","",N(Stock!$E18)+IF(LEFT(Stock!$C18,6)="Anillo",0,N(Stock!$D18))) -> 0 | G15: =IF(Costos!$A32="","",N(Stock!$F18)) -> 0 | H15: =IF(Costos!$A32="","",N(Stock!$G18)) -> 0 | K15: =IF(Costos!$A32="","",N(Stock!$J18)) -> 2
A16: =IF(Costos!$A33="","",Costos!$A33) -> Anillo Gota | B16: =IF(Costos!$A33="","",Costos!$B33&"") -> Plata 925 | C16: =IF(Costos!$A33="","",Costos!$C33&"") -> Anillo | D16: =IF(Costos!$A33="","",N(Costos!$K33)) -> 23000 | E16: =IF(Costos!$A33="","",N(Stock!$H19)) -> 0 | F16: =IF(Costos!$A33="","",N(Stock!$E19)+IF(LEFT(Stock!$C19,6)="Anillo",0,N(Stock!$D19))) -> 0 | G16: =IF(Costos!$A33="","",N(Stock!$F19)) -> 0 | H16: =IF(Costos!$A33="","",N(Stock!$G19)) -> 0 | K16: =IF(Costos!$A33="","",N(Stock!$J19)) -> 1
A17: =IF(Costos!$A34="","",Costos!$A34) -> Anillo Vera Docha | B17: =IF(Costos!$A34="","",Costos!$B34&"") -> Plata 925 | C17: =IF(Costos!$A34="","",Costos!$C34&"") -> Anillo | D17: =IF(Costos!$A34="","",N(Costos!$K34)) -> 13000 | E17: =IF(Costos!$A34="","",N(Stock!$H20)) -> 1 | F17: =IF(Costos!$A34="","",N(Stock!$E20)+IF(LEFT(Stock!$C20,6)="Anillo",0,N(Stock!$D20))) -> 0 | G17: =IF(Costos!$A34="","",N(Stock!$F20)) -> 0 | H17: =IF(Costos!$A34="","",N(Stock!$G20)) -> 1 | K17: =IF(Costos!$A34="","",N(Stock!$J20)) -> 0
... A126: =IF(Costos!$A143="","",Costos!$A143) | B126: =IF(Costos!$A143="","",Costos!$B143&"") | C126: =IF(Costos!$A143="","",Costos!$C143&"") | D126: =IF(Costos!$A143="","",N(Costos!$K143)) | E126: =IF(Costos!$A143="","",N(Stock!$H129)) | F126: =IF(Costos!$A143="","",N(Stock!$E129)+IF(LEFT(Stock!$C129,6)="Anillo",0,N(Stock!$D129))) | G126: =IF(Costos!$A143="","",N(Stock!$F129)) | H126: =IF(Costos!$A143="","",N(Stock!$G129)) | K126: =IF(Costos!$A143="","",N(Stock!$J129))
A129: Cómo se usa esta hoja
A130: • Producto, Material, Categoría, Precio y Stock se traen solos. Si cambiás algo en Costos o en Stock, acá se actualiza.
A131: • Destacado: escribí sí en las cuatro piezas que querés que aparezcan en la portada de la web (una por categoría).
A132: • Foto (link): pegá el enlace de la imagen del producto. Si lo dejás vacío, la web muestra un fondo del color del material.
A133: • Precio: sale de la columna Precio de venta de Costos. Si está vacío, la pieza no se muestra en la web.
A134: • Stock: sale de Total en stock. Cuando llega a 0, la web la marca agotada y ofrece piezas similares.
A135: • Las celdas amarillas son las únicas que se completan a mano.

Sheet Encargos 
A1: ENCARGOS
A2: Una línea por cada pieza que te encargan y no tenés en stock.
A3: Pieza, proveedor, talle y estado son desplegables. El saldo se calcula solo. La fila 6 es un ejemplo: pisala.
A5: Fecha del pedido | B5: Clienta | C5: Contacto | D5: Pieza | E5: Proveedor | F5: Talle | G5: Cantidad | H5: Precio acordado | I5: Seña | J5: Saldo | K5: Estado | L5: Fecha estimada | M5: Notas | O5: RESUMEN
A6: 46261 | B6: Gaby de Simone | D6: Anillo Vena | E6: 925 ARG | F6: Único | G6: 1 | H6: {=IF($D6="","",IFERROR(INDEX(Costos!$K$23:$K$122,MATCH($D6,Costos!$A$23:$A$122,0)),""))} -> 25000 | I6: 0 | J6: =IF($D6="","",N($H6)*MAX(1,N($G6))-N($I6)) -> 25000 | K6: Pendiente | M6: talle normal (trabajo mama) | O6: Encargos abiertos | P6: =COUNTIFS($D$6:$D$105,"<>",$K$6:$K$105,"<>Entregado",$K$6:$K$105,"<>Cancelado") -> 6
A7: 46261 | B7: Vicky de la Riestra | D7: Anillo Vena | E7: 925 ARG | F7: Único | G7: 1 | H7: {=IF($D7="","",IFERROR(INDEX(Costos!$K$23:$K$122,MATCH($D7,Costos!$A$23:$A$122,0)),""))} -> 25000 | I7: 0 | J7: =IF($D7="","",N($H7)*MAX(1,N($G7))-N($I7)) -> 25000 | K7: Pendiente | M7: talle normal (trabajo mama) | O7: Señas cobradas | P7: =SUMIFS($I$6:$I$105,$K$6:$K$105,"<>Cancelado") -> 0
A8: 46261 | B8: Silvina | D8: Anillo Vena | E8: 925 ARG | F8: Único | G8: 1 | H8: {=IF($D8="","",IFERROR(INDEX(Costos!$K$23:$K$122,MATCH($D8,Costos!$A$23:$A$122,0)),""))} -> 25000 | J8: =IF($D8="","",N($H8)*MAX(1,N($G8))-N($I8)) -> 25000 | K8: Pendiente | M8: queria un talle mas (trabajo mama) | O8: Saldo por cobrar | P8: =SUMIFS($J$6:$J$105,$K$6:$K$105,"<>Entregado",$K$6:$K$105,"<>Cancelado") -> 126500
A9: 46275 | B9: Magali Almeida | C9: 11 6024 2165 | D9: Anillo Zafira | E9: Blert | F9: Único | G9: 1 | H9: {=IF($D9="","",IFERROR(INDEX(Costos!$K$23:$K$122,MATCH($D9,Costos!$A$23:$A$122,0)),""))} -> 13000 | J9: =IF($D9="","",N($H9)*MAX(1,N($G9))-N($I9)) -> 13000 | K9: Pendiente | M9: le dije que para el mes que viene | O9: Total comprometido | P9: =SUMPRODUCT(($D$6:$D$105<>"")*($K$6:$K$105<>"Cancelado")*N($H$6:$H$105)) -> 126500
A10: 46275 | B10: Magali Almeida | C10: 11 6024 2165 | D10: Anillo Corazón I | E10: Blert | F10: Único | G10: 1 | H10: {=IF($D10="","",IFERROR(INDEX(Costos!$K$23:$K$122,MATCH($D10,Costos!$A$23:$A$122,0)),""))} -> 13000 | J10: =IF($D10="","",N($H10)*MAX(1,N($G10))-N($I10)) -> 13000 | K10: Pendiente | M10: le dije que para el mes que viene
A11: 46276 | B11: Mia Heredia | D11: Anillo Deriva | E11: 925 ARG | F11: Único | G11: 1 | H11: {=IF($D11="","",IFERROR(INDEX(Costos!$K$23:$K$122,MATCH($D11,Costos!$A$23:$A$122,0)),""))} -> 25500 | J11: =IF($D11="","",N($H11)*MAX(1,N($G11))-N($I11)) -> 25500 | K11: Pendiente | O11: Cuando la pieza llegue y la entregues, cargá la venta en la hoja Ventas y poné Entregado acá.
H12: {=IF($D12="","",IFERROR(INDEX(Costos!$K$23:$K$122,MATCH($D12,Costos!$A$23:$A$122,0)),""))} | J12: =IF($D12="","",N($H12)*MAX(1,N($G12))-N($I12)) | O12: El desplegable de Pieza toma la lista de productos de la hoja Costos (A23:A122).
H13: {=IF($D13="","",IFERROR(INDEX(Costos!$K$23:$K$122,MATCH($D13,Costos!$A$23:$A$122,0)),""))} | J13: =IF($D13="","",N($H13)*MAX(1,N($G13))-N($I13))
H14: {=IF($D14="","",IFERROR(INDEX(Costos!$K$23:$K$122,MATCH($D14,Costos!$A$23:$A$122,0)),""))} | J14: =IF($D14="","",N($H14)*MAX(1,N($G14))-N($I14))
H15: {=IF($D15="","",IFERROR(INDEX(Costos!$K$23:$K$122,MATCH($D15,Costos!$A$23:$A$122,0)),""))} | J15: =IF($D15="","",N($H15)*MAX(1,N($G15))-N($I15))
H16: {=IF($D16="","",IFERROR(INDEX(Costos!$K$23:$K$122,MATCH($D16,Costos!$A$23:$A$122,0)),""))} | J16: =IF($D16="","",N($H16)*MAX(1,N($G16))-N($I16))
H17: {=IF($D17="","",IFERROR(INDEX(Costos!$K$23:$K$122,MATCH($D17,Costos!$A$23:$A$122,0)),""))} | J17: =IF($D17="","",N($H17)*MAX(1,N($G17))-N($I17))
H18: {=IF($D18="","",IFERROR(INDEX(Costos!$K$23:$K$122,MATCH($D18,Costos!$A$23:$A$122,0)),""))} | J18: =IF($D18="","",N($H18)*MAX(1,N($G18))-N($I18))
H19: {=IF($D19="","",IFERROR(INDEX(Costos!$K$23:$K$122,MATCH($D19,Costos!$A$23:$A$122,0)),""))} | J19: =IF($D19="","",N($H19)*MAX(1,N($G19))-N($I19))
H20: {=IF($D20="","",IFERROR(INDEX(Costos!$K$23:$K$122,MATCH($D20,Costos!$A$23:$A$122,0)),""))} | J20: =IF($D20="","",N($H20)*MAX(1,N($G20))-N($I20))
H21: {=IF($D21="","",IFERROR(INDEX(Costos!$K$23:$K$122,MATCH($D21,Costos!$A$23:$A$122,0)),""))} | J21: =IF($D21="","",N($H21)*MAX(1,N($G21))-N($I21))
H22: {=IF($D22="","",IFERROR(INDEX(Costos!$K$23:$K$122,MATCH($D22,Costos!$A$23:$A$122,0)),""))} | J22: =IF($D22="","",N($H22)*MAX(1,N($G22))-N($I22))
H23: {=IF($D23="","",IFERROR(INDEX(Costos!$K$23:$K$122,MATCH($D23,Costos!$A$23:$A$122,0)),""))} | J23: =IF($D23="","",N($H23)*MAX(1,N($G23))-N($I23))
H24: {=IF($D24="","",IFERROR(INDEX(Costos!$K$23:$K$122,MATCH($D24,Costos!$A$23:$A$122,0)),""))} | J24: =IF($D24="","",N($H24)*MAX(1,N($G24))-N($I24))
... H105: {=IF($D105="","",IFERROR(INDEX(Costos!$K$23:$K$122,MATCH($D105,Costos!$A$23:$A$122,0)),""))} | J105: =IF($D105="","",N($H105)*MAX(1,N($G105))-N($I105))
H106: {=IF($D106="","",IFERROR(INDEX(Costos!$K$23:$K$122,MATCH($D106,Costos!$A$23:$A$122,0)),""))}

Sheet Inversión
A1: INVERSIÓN Y RECUPERO
A2: Acá va SOLO lo que no es mercadería: publicidad, exhibidores, envíos, packaging suelto.
A3: La mercadería la toma sola de la hoja Compras. Amarillo = lo completás vos.
A5: Fecha | B5: Concepto | C5: Categoría | D5: Origen | E5: Monto | G5: Fecha de corte de la inversión inicial | H5: 46260
A6: 46244 | B6: Publicidad Instagram | C6: publicidad | D6: bolsillo | E6: 35000
A7: 46244 | B7: Publicidad TikTok | C7: publicidad | D7: bolsillo | E7: 6500 | G7: 1. INVERSIÓN INICIAL — lo que hay que devolverse
A8: 46266 | B8: Publicidad Instagram | C8: publicidad | D8: ventas | E8: 22000 | G8: Mercadería de las primeras compras | H8: =SUMIFS(Compras!$F$6:$F$605,Compras!$A$6:$A$605,"<="&$H$5) -> 535635.24
A9: 46266 | B9: Publicidad Instagram | C9: publicidad | D9: ventas | E9: 10000 | G9: Exhibidores, publicidad y envíos | H9: =SUMIFS($E$6:$E$300,$A$6:$A$300,"<="&$H$5) -> 41500
A10: 46272 | B10: Envio Utopias | C10: envíos | D10: ventas | E10: 9800 | G10: TOTAL INVERSIÓN INICIAL | H10: =H8+H9 -> 577135.24
A11: 46272 | B11: Envio Cata | C11: envíos | D11: ventas | E11: 7500 | G11: Cobrado por ventas | H11: =SUM(Ventas!$F$6:$F$605) -> 978500
A12: 46274 | B12: Envio Plata 925 Reinas | C12: envíos | D12: ventas | E12: 8915 | G12: FALTA RECUPERAR | H12: =MAX(0,H10-H11) -> 0
G13: % recuperado | H13: =IF(H10=0,"",MIN(1,H11/H10)) -> 1
G15: 2. REPOSICIÓN — todo lo comprado después del corte
G16: Mercadería repuesta | H16: =SUM(Compras!$F$6:$F$605)-H8 -> 785727.07
G17: Puesta de mi bolsillo | H17: =SUMIFS($E$6:$E$300,$D$6:$D$300,"bolsillo",$A$6:$A$300,">"&$H$5) -> 0
G18: Pagada con las ventas | H18: =H16-H17 -> 785727.07
G20: 3. CÓMO VA EL NEGOCIO
G21: Costo de lo vendido | H21: =SUMPRODUCT(SUMIF(Costos!$A$23:$A$200,Ventas!$B$6:$B$605,Costos!$I$23:$I$200)*Ventas!$D$6:$D$605) -> 565881.1
G22: Recuperado de mi bolsillo hasta hoy | H22: 0
G23: Falta recuperar | H23: =559000-H22 -> 559000
G24: Plata disponible hoy | H24: =H11-H16-SUMIFS($E$6:$E$300,$A$6:$A$300,">"&$H$5,$D$6:$D$300,"ventas") -> 134557.93
G30: La inversión inicial se congela con la fecha de corte: todo lo comprado hasta
G31: ese día es plata tuya a recuperar. Lo de después es reposición y no mueve la meta.
G32: Ojo: las compras sin fecha no entran en el cálculo. Fijate que todas tengan.
G33: "En la mano hoy" es lo cobrado menos lo que ya volviste a gastar después del corte.
G34: Si pagaste un pedido que todavía no llegó, cargalo arriba como gasto con origen "ventas"
G35: y borrá esa fila cuando lo cargues en Compras.

Sheet Warmichella
B2: Warmichella Navidad — 12 y 13 de diciembre
B3: Stand MESA · Parque Náutico de San Fernando · 12 a 20 hs
B5: LO QUE HAY QUE CUBRIR
B6: Stand mesa, IVA incluido | C6: 600000 | D6: por los dos días
B8: TUS NÚMEROS POR PIEZA
B9: Precio de venta promedio | C9: 20000
B10: Costo promedio de la pieza | C10: 10000 | D10: lo que te sale a vos
B11: Packaging por pieza | C11: 1500
B12: Te queda por pieza | C12: =C9-C10-C11 -> 8500
B13: Eso es, del precio | C13: =IF(C9=0,"",C12/C9) -> 0.425
B15: PUNTO DE EQUILIBRIO
B16: Piezas que tenés que vender | C16: =IF(C12<=0,"",ROUNDUP(C6/C12,0)) -> 71
B17: Eso en plata (facturación) | C17: =IF(C16="","",C16*C9) -> 1420000
B18: Por día (son 2 días) | C18: =IF(C16="","",ROUNDUP(C16/2,0)) -> 36
B19: Por hora (8 hs por día) | C19: =IF(C16="","",ROUND(C16/16,1)) -> 4.4
B20: El stand se come, de cada venta | C20: =IF(C16="","",C6/C16/C9) -> 0.42253521
B22: SI VENDÉS MÁS O MENOS
B23: Piezas vendidas | C23: Facturación | D23: Te queda | E23: Resultado | F23: El stand se lleva
B24: 40 | C24: =B24*$C$9 -> 800000 | D24: =B24*$C$12 -> 340000 | E24: =D24-$C$6 -> -260000 | F24: =$C$6/B24/$C$9 -> 0.75
B25: 60 | C25: =B25*$C$9 -> 1200000 | D25: =B25*$C$12 -> 510000 | E25: =D25-$C$6 -> -90000 | F25: =$C$6/B25/$C$9 -> 0.5
B26: =$C$16 -> 71 | C26: =B26*$C$9 -> 1420000 | D26: =B26*$C$12 -> 603500 | E26: =D26-$C$6 -> 3500 | F26: =$C$6/B26/$C$9 -> 0.42253521 | G26: punto de equilibrio
B27: 80 | C27: =B27*$C$9 -> 1600000 | D27: =B27*$C$12 -> 680000 | E27: =D27-$C$6 -> 80000 | F27: =$C$6/B27/$C$9 -> 0.375
B28: 100 | C28: =B28*$C$9 -> 2000000 | D28: =B28*$C$12 -> 850000 | E28: =D28-$C$6 -> 250000 | F28: =$C$6/B28/$C$9 -> 0.3
B29: 120 | C29: =B29*$C$9 -> 2400000 | D29: =B29*$C$12 -> 1020000 | E29: =D29-$C$6 -> 420000 | F29: =$C$6/B29/$C$9 -> 0.25
B30: 150 | C30: =B30*$C$9 -> 3000000 | D30: =B30*$C$12 -> 1275000 | E30: =D30-$C$6 -> 675000 | F30: =$C$6/B30/$C$9 -> 0.2
B31: 200 | C31: =B31*$C$9 -> 4000000 | D31: =B31*$C$12 -> 1700000 | E31: =D31-$C$6 -> 1100000 | F31: =$C$6/B31/$C$9 -> 0.15
B34: Cómo se usa
B35: • Completá solo las celdas amarillas. Todo lo demás se calcula solo.
B36: • El precio y el costo promedio salen de tu hoja Costos: promediá lo que pensás llevar a la feria.
B37: • "El stand se come, de cada venta" es la parte de cada precio que se va en pagar la mesa.
B38: • Cuanto más vendas, más chica es esa parte: es el mismo costo fijo repartido entre más piezas.
B39: Fuente del precio del stand: mensaje de la organización, MESA $600.000 IVA incluido por los dos días.

Sheet Hoja 1
A1: 1. PACKAGING - CAJA BOLSA
A2: Componente | B2: Precio del pack | C2: Unidades | D2: Costo por pieza | E2: Descripción del pedido | F2: Notas | H2: CONTRAS
A3: CAJA BOLSA | B3: 1840 | C3: 1 | D3: =IFERROR(B3/C3,0) -> 1840 | E3: FARINAPACK | H3: El problema es que tendria que comprar 200 unidades que me da un total de $368.000
A4: Etiqueta interior | B4: 2783 | C4: 60 | D4: =IFERROR(B4/C4,0) -> 46.383333 | E4: Ideas Argentinas. Tarjeta 8x5 cm horizontal, ilustración 300 gr, frente y dorso. Frente con logo, dorso manteca liso. Entran 30 por hoja A3+ (31x46 cm). 2 impresiones = $2.300 + IVA = 60 tarjetas. Mitad plata 925, mitad acero blanco. Falta confirmar el corte con guillotina (piden mínimo 10 impresiones).
A5: TOTAL PACKAGING POR PIEZA | D5: =SUM(D3:D4) -> 1886.3833
A8: 2. PACKAGING CAJA + BOLSA LIENZO
A9: Componente | B9: Precio del pack | C9: Unidades | D9: Costo por pieza | E9: Descripción del pedido | F9: Notas
A10: Sticker isotipo | B10: 1936 | C10: 70 | D10: =IFERROR(B10/C10,0) -> 27.657143 | E10: Ideas Argentinas. Redondo 3,5 cm, fondo chocolate con la O manteca, papel adhesivo, troquelado incluido. 1 plancha de 29x40 cm = $1.600 + IVA. Producción normal 48/72 hs. Falta que confirmen cuántos entran por plancha (estimado 70, con 3 mm entre siluetas). | F10: En Oink salen $17.100 por 240u ($71 c/u). En Studio Imagene $16.000 por 300u en vinilo, con muestra sin cargo. | H10: CONTRAS
A11: Etiqueta interior | B11: 2783 | C11: 60 | D11: =IFERROR(B11/C11,0) -> 46.383333 | E11: Ideas Argentinas. Tarjeta 8x5 cm horizontal, ilustración 300 gr, frente y dorso. Frente con logo, dorso manteca liso. Entran 30 por hoja A3+ (31x46 cm). 2 impresiones = $2.300 + IVA = 60 tarjetas. Mitad plata 925, mitad acero blanco. | F11: Oink cobra $23.000 por 100 unidades. Studio Imagene no trabaja cartón. | H11: - No encuentro bolsas de cartulina blancas baratas
A12: Caja kraft chica | B12: 24364 | C12: 50 | D12: =IFERROR(B12/C12,0) -> 487.28 | E12: Caja en 1 pieza 7x7x2 cm, color kraft (marrón), cartulina kraft 280 gr, autoarmable. Mínimo de compra 10 unidades. Precio para 50 unidades, IVA incluido ($487/u). | F12: Precio con descuento ya aplicado (antes $27.071, ahora $24.364). También existe en cartulina blanca Triplex 275 gr al mismo precio. | H12: - No se si quedara muy vacio el anillo directo en ña bolsa de lienzo que mide 9x10
A13: bolsa lienzo | B13: 24190 | C13: 50 | D13: =IFERROR(B13/C13,0) -> 483.8 | E13: Bolsa de ahorque N1, 9x10 cm, lisa (sin estampar), pack x50.
A14: Bolsa con manija | C14: 40 | D14: =IFERROR(B14/C14,0) -> 0 | E14: Bolsa de papel con manija para entregas en mano. Sin cotizar todavía.
A15: TOTAL PACKAGING POR PIEZA | D15: =SUM(D10:D14) -> 1045.1205
A18: 3. PACKAGING CARTÓN PERSONALIZADO + BOLSA LIENZO
A19: Componente | B19: Precio del pack | C19: Unidades | D19: Costo por pieza | E19: Descripción del pedido | F19: proceso
A20: Sticker isotipo | B20: 1936 | C20: 70 | D20: =IFERROR(B20/C20,0) -> 27.657143 | E20: Ideas Argentinas. Redondo 3,5 cm, fondo chocolate con la O manteca, papel adhesivo, troquelado incluido. 1 plancha de 29x40 cm = $1.600 + IVA. Producción normal 48/72 hs. Falta que confirmen cuántos entran por plancha (estimado 70, con 3 mm entre siluetas). | F20: fijarme el color para pagarle a roxana e imprimir
A21: Etiqueta interior | B21: 2783 | C21: 60 | D21: =IFERROR(B21/C21,0) -> 46.383333 | E21: Ideas Argentinas. Tarjeta 8x5 cm horizontal, ilustración 300 gr, frente y dorso. Frente con logo, dorso manteca liso. Entran 30 por hoja A3+ (31x46 cm). 2 impresiones = $2.300 + IVA = 60 tarjetas. Mitad plata 925, mitad acero blanco. | F21: tengo que ir a retirar a larralde
A22: Cartón personalizado | F22: fijarme si sirven las tarjetas interiores
A23: Caja Kraft | B23: 5414 | C23: 10 | D23: =IFERROR(B23/C23,0) -> 541.4 | F23: compre en smartpackaging, me queda retirarlo x ramallo
A24: Sticker cerrar caja | B24: 16500 | C24: 160 | D24: =IFERROR(B24/C24,0) -> 103.125 | F24: mande a studioimage falta q contesten
A25: Bolsa autoadhesiva | B25: 3220 | C25: 100 | D25: =IFERROR(B25/C25,0) -> 32.2 | E25: Bolsa autoadhesiva 6x11 | F25: compre por ML tengo que retirarlo
A26: Bolsa con manija | C26: 40 | D26: =IFERROR(B26/C26,0) -> 0 | E26: Bolsa de papel con manija para entregas en mano. Sin cotizar todavía.
A27: TOTAL PACKAGING POR PIEZA | D27: =SUM(D20:D26) -> 750.76548
